rtl/alu.sv
`timescale 1ns/100ps

module alu (
  input  wire [31:0] instruction_i,
  input  wire [31:0] rs1_data_i,
  input  wire [31:0] rs2_data_i,
//  input  wire [ 6:0] alu_opcode_i,
//  input  wire [ 2:0] alu_funct3_i,
//  input  wire [ 6:0] alu_funct7_i,
//  output wire        zero_o,
  output reg [31:0]  result_o
);

  wire [ 6:0] alu_opcode_s;
  wire [ 2:0] alu_funct3_s;
  wire [ 6:0] alu_funct7_s;
  wire [ 4:0] shamt_s;
  wire [11:0] imm_s;
//  typedef enum logic [4:0] {ADD, SUB, MUL, DIV, AND, OR, XOR, NOT, LEZ, LTZ, GTZ, EQT, NET} operation_t;
  parameter logic [6:0] RTYPE = 7'b0110011;
  parameter logic [6:0] ITYPE = 7'b0010011;

//  localparam logic [2:0] SUB  = 3'b000; // Shared funct3
  parameter logic [2:0] ADD_SUB  = 3'b000; // Shared funct3
  parameter logic [2:0] SLL      = 3'b001;
  parameter logic [2:0] SLT      = 3'b010;
  parameter logic [2:0] SLTU     = 3'b011;
  parameter logic [2:0] XOR      = 3'b100;
  parameter logic [2:0] SRL_SRA  = 3'b101; // Shared funct3
  parameter logic [2:0] OR       = 3'b110;
  parameter logic [2:0] AND      = 3'b111;

  parameter logic [2:0] ADDI      = 3'b000;
  parameter logic [2:0] SLTI      = 3'b010;
  parameter logic [2:0] SLTIU     = 3'b011;
  parameter logic [2:0] XORI      = 3'b100;
  parameter logic [2:0] ORI       = 3'b110;
  parameter logic [2:0] ANDI      = 3'b111;

  parameter logic [2:0] SLLI      = 3'b001;
  parameter logic [2:0] SRLI_SRAI = 3'b101; // Shared funct3

  assign imm_s        = instruction_i[31:20];
  assign shamt_s      = instruction_i[24:20];
  assign alu_opcode_s = instruction_i[ 6: 0];
  assign alu_funct3_s = instruction_i[14:12];
  assign alu_funct7_s = instruction_i[31:25];



//
//funct7   rs2    rs1  funct3  rd  opcode
//0000000  rs2    rs1  000     rd  0110011  ADD
//0100000  rs2    rs1  000     rd  0110011  SUB
//0000000  rs2    rs1  001     rd  0110011  SLL
//0000000  rs2    rs1  010     rd  0110011  SLT
//0000000  rs2    rs1  011     rd  0110011  SLTU
//0000000  rs2    rs1  100     rd  0110011  XOR
//0000000  rs2    rs1  101     rd  0110011  SRL
//0100000  rs2    rs1  101     rd  0110011  SRA
//0000000  rs2    rs1  110     rd  0110011  OR
//0000000  rs2    rs1  111     rd  0110011  AND


  always @(*) 
  begin
    result_o = 32'd0;
    if (alu_opcode_s == RTYPE)
    begin
      case(alu_funct3_s)
        ADD_SUB:
        begin
          if (!alu_funct7_s[5])
            result_o = rs1_data_i + rs2_data_i; 
          else
            result_o = rs1_data_i - rs2_data_i; 
        end
        SLL:  result_o = (rs1_data_i << rs2_data_i); 
        SLT:  result_o[0] = ($signed(rs1_data_i) < $signed(rs2_data_i)); 
        SLTU: result_o[0] = (rs1_data_i < rs2_data_i); 
        XOR:  result_o = rs1_data_i ^ rs2_data_i; 
        SRL_SRA:
        begin
          if (!alu_funct7_s[5])
            result_o = (rs1_data_i >> rs2_data_i); 
          else
            result_o = (rs1_data_i >>> rs2_data_i); 
        end
        OR:   result_o = rs1_data_i | rs2_data_i; 
        AND:  result_o = rs1_data_i & rs2_data_i; 

        default: 
          result_o = 32'hDEADC0DE; 
      endcase
    end
    else if (alu_opcode_s == ITYPE)
    begin
      case(alu_funct3_s)
        ADDI:      result_o    = rs1_data_i + {{20{imm_s[11]}}, imm_s}; 
        SLTI:      result_o[0] = ($signed(rs1_data_i) < $signed({{20{imm_s[11]}}, imm_s})); 
        SLTIU:     result_o[0] = (rs1_data_i < {{20{imm_s[11]}}, imm_s}); 
        XORI:      result_o    = rs1_data_i ^  {{20{imm_s[11]}}, imm_s};
        ORI:       result_o    = rs1_data_i |  {{20{imm_s[11]}}, imm_s};
        ANDI:      result_o    = rs1_data_i &  {{20{imm_s[11]}}, imm_s};  
        SLLI:      result_o    = (rs1_data_i << rs2_data_i);
        SRLI_SRAI:
        begin
          if (!instruction_i[30])
            result_o = (rs1_data_i >> shamt_s); 
          else
            result_o = (rs1_data_i >>> shamt_s); 
        end

        default:
          result_o = 32'hDEADC0DE; 
      endcase
    end
  end

//Immediate      rs1  f3   rd  opcode
//imm[11:0]      rs1  000  rd  0010011  ADDI
//imm[11:0]      rs1  010  rd  0010011  SLTI
//imm[11:0]      rs1  011  rd  0010011  SLTIU
//imm[11:0]      rs1  100  rd  0010011  XORI
//imm[11:0]      rs1  110  rd  0010011  ORI
//imm[11:0]      rs1  111  rd  0010011  ANDI
//0000000 shamt  rs1  001  rd  0010011  SLLI
//0000000 shamt  rs1  101  rd  0010011  SRLI
//0100000 shamt  rs1  101  rd  0010011  SRAI
 
//  assign zero_o = !(|result_o);

endmodule

rtl/regfile.sv
`timescale 1ns/100ps

module regfile #(parameter NUM_REGS=32)
(
  input          clk,     // Input clock
  input          rst_n,   // Reset (active-low)
  input          wr_en,   // Enable register write
  input   [ 4:0] rs1_i,   // Read source register 1
  input   [ 4:0] rs2_i,   // Read source register 2
  input   [ 4:0] wrd_i,   // Write destination register
  input   [31:0] wdata_i, // Write data in
  output  wire [31:0] rs1_o,   // Read data for RS1
  output  wire [31:0] rs2_o    // Read data for RS2
);
    

  reg [31:0] x [0:NUM_REGS-1];
//  logic [31:0] din  [0:NUM_REGS-1];

  always @(posedge clk or negedge rst_n) begin
    if (!rst_n)
    begin
//      din[wrd_i] <= 32'd0;
//      x[wrd_i] <= 32'd0;
      x[ 0] <= 32'd0;
      x[ 1] <= 32'd0;
      x[ 2] <= 32'd0;
      x[ 3] <= 32'd0;
      x[ 4] <= 32'd0;
      x[ 5] <= 32'd0;
      x[ 6] <= 32'd0;
      x[ 7] <= 32'd0;
      x[ 8] <= 32'd0;
      x[ 9] <= 32'd0;
      x[10] <= 32'd0;
      x[11] <= 32'd0;
      x[12] <= 32'd0;
      x[13] <= 32'd0;
      x[14] <= 32'd0;
      x[15] <= 32'd0;
      x[16] <= 32'd0;
      x[17] <= 32'd0;
      x[18] <= 32'd0;
      x[19] <= 32'd0;
      x[20] <= 32'd0;
      x[21] <= 32'd0;
      x[22] <= 32'd0;
      x[23] <= 32'd0;
      x[24] <= 32'd0;
      x[25] <= 32'd0;
      x[26] <= 32'd0;
      x[27] <= 32'd0;
      x[28] <= 32'd0;
      x[29] <= 32'd0;
      x[30] <= 32'd0;
      x[31] <= 32'd0;
    end
    else if (wr_en && (wrd_i != 5'd0)) begin
//      din[wrd_i] <= wdata_i;
      x[wrd_i] <= wdata_i;
    end
  end
    

  assign rs1_o = x[rs1_i];
  assign rs2_o = x[rs2_i];

endmodule

rtl/inst_mem.sv
`timescale 1ns/100ps

module  instruction_memory(
  input  wire [31:0] address_i,
  output reg  [31:0] instruction_o 
);

  reg [31:0] imem [0:255]; // 1KB instruction memory.
  
  initial begin
    $readmemb("inst.mem", imem);
  end

  always @(*)
  begin
    instruction_o = 32'd0;
    instruction_o = imem[address_i[9:2]];
  end

endmodule

rtl/reg32bit.sv
`timescale 1ns/100ps

module reg32bit (
  input        clk,
  input        rst_n,
  input        wr_en,
  input  wire [31:0] reg_i,
  output reg  [31:0] reg_o
);

  
  always @(posedge clk or negedge rst_n) begin
    if (!rst_n)
      reg_o <= 32'h00;
    else if (wr_en)
      reg_o <= reg_i;
    else
      reg_o <= reg_o;
  end
    
endmodule

rtl/ifu.sv
`timescale 1ns/100ps

// Instruction Fetch Unit
module ifu (
  input  wire clk,
  input  wire rst_n,
  output wire [31:0] instruction_o
);

  wire [31:0] next_pc;
  wire [31:0] pc;
  wire [31:0] inst;

  // Program Counter 32-bit register
  reg32bit reg32bit_pc_inst(.clk  (clk),
                            .rst_n(rst_n),
                            .wr_en(1'b1), // PC write_enable tied high for now
                            .reg_i(next_pc),
                            .reg_o(pc));

  assign next_pc = pc + 32'd4; // Add 4 bytes for the next Program Counter

  instruction_memory instruction_memory_inst(.address_i(pc),
                                             .instruction_o(instruction_o));

endmodule

rtl/clk_gen.sv
`timescale 1ns/100ps
module clk_gen (output reg clk);
    
/* verilator lint_off INFINITELOOP */
/* verilator lint_off STMTDLY */
    always begin
        
      clk = 0;
      forever #5  clk = ~clk;
    end
/* verilator lint_on STMTDLY */
/* verilator lint_on INFINITELOOP */

endmodule

rtl/cpu_top.sv
`timescale 1ns/100ps

module cpu_top(
  input         rst_n,
  input         wr_en,
//  input  [ 4:0] rs1_i,
//  input  [ 4:0] rs2_i,
//  input  [ 4:0] wrd_i,
  input  [ 6:0] alu_op_i,
  input  [31:0] wdata_i,
  input  [31:0] mem_rdata_i,
  output [31:0] alu_result_o,
  output        z_flag_o

);

  wire sysclk;
  wire [31:0] rs1_data, rs2_data, instruction_s, alu_result_s;

  assign alu_result_o = alu_result_s;

  // Instantiation of a clk_gen block
  clk_gen clk_gen_inst(.clk(sysclk));

  // Fetch: includes PC + instruction memory
  ifu ifu_inst(.clk(sysclk),
               .rst_n(rst_n),
               .instruction_o(instruction_s));

  // Decode: includes a regfile (minimal decode for now) TODO: improve decode
  // stage
  // Instantiation of a register file with 32x 32-bit registers
  regfile regfile_inst(.clk    (sysclk),
                       .rst_n  (rst_n),
                       .wr_en  (wr_en),
                       .rs1_i  (instruction_s[19:15]),
                       .rs2_i  (instruction_s[24:20]),
                       .wrd_i  (instruction_s[11: 7]),
                       .wdata_i(alu_result_s),
                       .rs1_o  (rs1_data),
                       .rs2_o  (rs2_data)
                       );

  // Execute: includes ALU module
  alu alu_inst (
    .instruction_i(instruction_s),
    .rs1_data_i   (rs1_data),
    .rs2_data_i   (rs2_data),
    .result_o     (alu_result_s)
  );
endmodule

tb/tb_top.sv
`timescale 1ns/100ps

module tb_top;

  reg          rst_n;
  reg          wr_en    = 1'b0;
  reg   [ 4:0] rs1_i    = 5'd0;
  reg   [ 4:0] rs2_i    = 5'd0;
  reg   [ 4:0] wrd_i    = 5'd0;
  reg   [31:0] wdata_i  = 32'd0;
  reg   [ 6:0] alu_op_i = 4'd0;
  integer i;
      
  // Instantiation of a reg32bit block
  cpu_top cpu_top_inst(.rst_n(rst_n),
                       .wr_en(wr_en),
                       //.rs1_i(rs1_i),
                       //.rs2_i(rs2_i),
                       //.wrd_i(wrd_i),
                       .wdata_i(wdata_i),
                       .alu_op_i(alu_op_i),
                       .mem_rdata_i(32'd0),
                       .alu_result_o(),
                       .z_flag_o());

  // data signals
  //wire  [31:0] rs1_o;
  //wire  [31:0] rs2_o;

  // Generation of dumpfile for GTKWave
   initial begin
    $dumpfile("cpu_dump.vcd");
    $dumpvars(0, tb_top);//, clk_gen_inst, regfile_inst, reg_32bit_inst);
    for (i=0; i<32;i++)
      $dumpvars(0,cpu_top_inst.regfile_inst.x[i]);
  end
 
  // Test procedure
  initial begin
    // reset
    rst_n = 1'b0;
    wdata_i  = 32'd0;
    #10
    rst_n = 1'b1;
    #1
    wr_en = 1'b1;
    
    #100
    #1000
//    wrd_i = 5'd13;
//    rs1_i = 5'd13;
//    wdata_i = 32'h00FF00FF;
//    #10
//    alu_op_i = 4'd4;
//    #10
//    wrd_i = 5'd10;
//    wdata_i = 32'h11FF11FF;
//    rs2_i = 5'd10;
//
//    #50
//    alu_op_i = 4'd9;
//    #20
//    wrd_i = 5'd23;
//    rs1_i = 5'd23;
//    wdata_i = 32'hFFFF0000;
//
//    #50
//    wdata_i = 32'hDEADBEEF;
//
//    #50
//    wrd_i = 5'd0;
//    rs1_i = 5'd0;
//    wdata_i = 32'hFFFF0000;

    #50
    rst_n = 1'b0;
    #100
    rst_n = 1'b1;
    #50

    $display("Vacuous Pass!"); // Yeah, that easy!
    $finish;
  end

endmodule

sim/cpu_dump.vcd
$date
	Sat Dec 25 13:59:19 2021
$end
$version
	Icarus Verilog
$end
$timescale
	100ps
$end
$scope module tb_top $end
$var reg 7 ! alu_op_i [6:0] $end
$var reg 5 " rs1_i [4:0] $end
$var reg 5 # rs2_i [4:0] $end
$var reg 1 $ rst_n $end
$var reg 32 % wdata_i [31:0] $end
$var reg 1 & wr_en $end
$var reg 5 ' wrd_i [4:0] $end
$var integer 32 ( i [31:0] $end
$scope module cpu_top_inst $end
$var wire 7 ) alu_op_i [6:0] $end
$var wire 32 * alu_result_o [31:0] $end
$var wire 32 + mem_rdata_i [31:0] $end
$var wire 1 $ rst_n $end
$var wire 32 , wdata_i [31:0] $end
$var wire 1 & wr_en $end
$var wire 1 - z_flag_o $end
$var wire 1 . sysclk $end
$var wire 32 / rs2_data [31:0] $end
$var wire 32 0 rs1_data [31:0] $end
$var wire 32 1 instruction_s [31:0] $end
$var wire 32 2 alu_result_s [31:0] $end
$scope module alu_inst $end
$var wire 5 3 shamt_s [4:0] $end
$var wire 32 4 rs2_data_i [31:0] $end
$var wire 32 5 rs1_data_i [31:0] $end
$var wire 32 6 instruction_i [31:0] $end
$var wire 12 7 imm_s [11:0] $end
$var wire 7 8 alu_opcode_s [6:0] $end
$var wire 7 9 alu_funct7_s [6:0] $end
$var wire 3 : alu_funct3_s [2:0] $end
$var reg 32 ; result_o [31:0] $end
$upscope $end
$scope module clk_gen_inst $end
$var reg 1 . clk $end
$upscope $end
$scope module ifu_inst $end
$var wire 1 . clk $end
$var wire 1 $ rst_n $end
$var wire 32 < pc [31:0] $end
$var wire 32 = next_pc [31:0] $end
$var wire 32 > instruction_o [31:0] $end
$scope module instruction_memory_inst $end
$var wire 32 ? address_i [31:0] $end
$var reg 32 @ instruction_o [31:0] $end
$upscope $end
$scope module reg32bit_pc_inst $end
$var wire 1 . clk $end
$var wire 32 A reg_i [31:0] $end
$var wire 1 $ rst_n $end
$var wire 1 B wr_en $end
$var reg 32 C reg_o [31:0] $end
$upscope $end
$upscope $end
$scope module regfile_inst $end
$var wire 1 . clk $end
$var wire 5 D rs1_i [4:0] $end
$var wire 32 E rs1_o [31:0] $end
$var wire 5 F rs2_i [4:0] $end
$var wire 32 G rs2_o [31:0] $end
$var wire 1 $ rst_n $end
$var wire 32 H wdata_i [31:0] $end
$var wire 1 & wr_en $end
$var wire 5 I wrd_i [4:0] $end
$upscope $end
$upscope $end
$upscope $end
$scope module tb_top $end
$scope module cpu_top_inst $end
$scope module regfile_inst $end
$var reg 32 J \x[0] [31:0] $end
$upscope $end
$upscope $end
$upscope $end
$scope module tb_top $end
$scope module cpu_top_inst $end
$scope module regfile_inst $end
$var reg 32 K \x[1] [31:0] $end
$upscope $end
$upscope $end
$upscope $end
$scope module tb_top $end
$scope module cpu_top_inst $end
$scope module regfile_inst $end
$var reg 32 L \x[2] [31:0] $end
$upscope $end
$upscope $end
$upscope $end
$scope module tb_top $end
$scope module cpu_top_inst $end
$scope module regfile_inst $end
$var reg 32 M \x[3] [31:0] $end
$upscope $end
$upscope $end
$upscope $end
$scope module tb_top $end
$scope module cpu_top_inst $end
$scope module regfile_inst $end
$var reg 32 N \x[4] [31:0] $end
$upscope $end
$upscope $end
$upscope $end
$scope module tb_top $end
$scope module cpu_top_inst $end
$scope module regfile_inst $end
$var reg 32 O \x[5] [31:0] $end
$upscope $end
$upscope $end
$upscope $end
$scope module tb_top $end
$scope module cpu_top_inst $end
$scope module regfile_inst $end
$var reg 32 P \x[6] [31:0] $end
$upscope $end
$upscope $end
$upscope $end
$scope module tb_top $end
$scope module cpu_top_inst $end
$scope module regfile_inst $end
$var reg 32 Q \x[7] [31:0] $end
$upscope $end
$upscope $end
$upscope $end
$scope module tb_top $end
$scope module cpu_top_inst $end
$scope module regfile_inst $end
$var reg 32 R \x[8] [31:0] $end
$upscope $end
$upscope $end
$upscope $end
$scope module tb_top $end
$scope module cpu_top_inst $end
$scope module regfile_inst $end
$var reg 32 S \x[9] [31:0] $end
$upscope $end
$upscope $end
$upscope $end
$scope module tb_top $end
$scope module cpu_top_inst $end
$scope module regfile_inst $end
$var reg 32 T \x[10] [31:0] $end
$upscope $end
$upscope $end
$upscope $end
$scope module tb_top $end
$scope module cpu_top_inst $end
$scope module regfile_inst $end
$var reg 32 U \x[11] [31:0] $end
$upscope $end
$upscope $end
$upscope $end
$scope module tb_top $end
$scope module cpu_top_inst $end
$scope module regfile_inst $end
$var reg 32 V \x[12] [31:0] $end
$upscope $end
$upscope $end
$upscope $end
$scope module tb_top $end
$scope module cpu_top_inst $end
$scope module regfile_inst $end
$var reg 32 W \x[13] [31:0] $end
$upscope $end
$upscope $end
$upscope $end
$scope module tb_top $end
$scope module cpu_top_inst $end
$scope module regfile_inst $end
$var reg 32 X \x[14] [31:0] $end
$upscope $end
$upscope $end
$upscope $end
$scope module tb_top $end
$scope module cpu_top_inst $end
$scope module regfile_inst $end
$var reg 32 Y \x[15] [31:0] $end
$upscope $end
$upscope $end
$upscope $end
$scope module tb_top $end
$scope module cpu_top_inst $end
$scope module regfile_inst $end
$var reg 32 Z \x[16] [31:0] $end
$upscope $end
$upscope $end
$upscope $end
$scope module tb_top $end
$scope module cpu_top_inst $end
$scope module regfile_inst $end
$var reg 32 [ \x[17] [31:0] $end
$upscope $end
$upscope $end
$upscope $end
$scope module tb_top $end
$scope module cpu_top_inst $end
$scope module regfile_inst $end
$var reg 32 \ \x[18] [31:0] $end
$upscope $end
$upscope $end
$upscope $end
$scope module tb_top $end
$scope module cpu_top_inst $end
$scope module regfile_inst $end
$var reg 32 ] \x[19] [31:0] $end
$upscope $end
$upscope $end
$upscope $end
$scope module tb_top $end
$scope module cpu_top_inst $end
$scope module regfile_inst $end
$var reg 32 ^ \x[20] [31:0] $end
$upscope $end
$upscope $end
$upscope $end
$scope module tb_top $end
$scope module cpu_top_inst $end
$scope module regfile_inst $end
$var reg 32 _ \x[21] [31:0] $end
$upscope $end
$upscope $end
$upscope $end
$scope module tb_top $end
$scope module cpu_top_inst $end
$scope module regfile_inst $end
$var reg 32 ` \x[22] [31:0] $end
$upscope $end
$upscope $end
$upscope $end
$scope module tb_top $end
$scope module cpu_top_inst $end
$scope module regfile_inst $end
$var reg 32 a \x[23] [31:0] $end
$upscope $end
$upscope $end
$upscope $end
$scope module tb_top $end
$scope module cpu_top_inst $end
$scope module regfile_inst $end
$var reg 32 b \x[24] [31:0] $end
$upscope $end
$upscope $end
$upscope $end
$scope module tb_top $end
$scope module cpu_top_inst $end
$scope module regfile_inst $end
$var reg 32 c \x[25] [31:0] $end
$upscope $end
$upscope $end
$upscope $end
$scope module tb_top $end
$scope module cpu_top_inst $end
$scope module regfile_inst $end
$var reg 32 d \x[26] [31:0] $end
$upscope $end
$upscope $end
$upscope $end
$scope module tb_top $end
$scope module cpu_top_inst $end
$scope module regfile_inst $end
$var reg 32 e \x[27] [31:0] $end
$upscope $end
$upscope $end
$upscope $end
$scope module tb_top $end
$scope module cpu_top_inst $end
$scope module regfile_inst $end
$var reg 32 f \x[28] [31:0] $end
$upscope $end
$upscope $end
$upscope $end
$scope module tb_top $end
$scope module cpu_top_inst $end
$scope module regfile_inst $end
$var reg 32 g \x[29] [31:0] $end
$upscope $end
$upscope $end
$upscope $end
$scope module tb_top $end
$scope module cpu_top_inst $end
$scope module regfile_inst $end
$var reg 32 h \x[30] [31:0] $end
$upscope $end
$upscope $end
$upscope $end
$scope module tb_top $end
$scope module cpu_top_inst $end
$scope module regfile_inst $end
$var reg 32 i \x[31] [31:0] $end
$upscope $end
$upscope $end
$upscope $end
$enddefinitions $end
#0
$dumpvars
b0 i
b0 h
b0 g
b0 f
b0 e
b0 d
b0 c
b0 b
b0 a
b0 `
b0 _
b0 ^
b0 ]
b0 \
b0 [
b0 Z
b0 Y
b0 X
b0 W
b0 V
b0 U
b0 T
b0 S
b0 R
b0 Q
b0 P
b0 O
b0 N
b0 M
b0 L
b0 K
b0 J
b10000 I
b0 H
b0 G
b10100 F
b0 E
b1 D
b0 C
1B
b100 A
b1010000001000100000110011 @
b0 ?
b1010000001000100000110011 >
b100 =
b0 <
b0 ;
b0 :
b0 9
b110011 8
b10100 7
b1010000001000100000110011 6
b0 5
b0 4
b10100 3
b0 2
b1010000001000100000110011 1
b0 0
b0 /
0.
z-
b0 ,
b0 +
b0 *
b0 )
b100000 (
b0 '
0&
b0 %
0$
b0 #
b0 "
b0 !
$end
#50
b0 i
b0 h
b0 g
b0 f
b0 e
b0 d
b0 c
b0 b
b0 a
b0 `
b0 _
b0 ^
b0 ]
b0 \
b0 [
b0 Z
b0 Y
b0 X
b0 W
b0 V
b0 U
b0 T
b0 S
b0 R
b0 Q
b0 P
b0 O
b0 N
b0 M
b0 L
b0 K
b0 J
1.
#100
0.
1$
#110
1&
#150
b1 *
b1 2
b1 ;
b1 H
b10011 8
b1 3
b1 7
b1 I
b1 F
b0 D
b100000000000010010011 1
b100000000000010010011 6
b100000000000010010011 >
b100000000000010010011 @
b1000 =
b1000 A
b100 <
b100 ?
b100 C
b0 Z
1.
#200
0.
#250
b10 3
b10 7
b10 I
b10 F
b10 *
b10 2
b10 ;
b10 H
b1000000000000100010011 1
b1000000000000100010011 6
b1000000000000100010011 >
b1000000000000100010011 @
b1 K
b0 /
b0 4
b0 G
b1100 =
b1100 A
b1000 <
b1000 ?
b1000 C
1.
#300
0.
#350
b11 3
b11 7
b11 I
b11 F
b1100000000000110010011 1
b1100000000000110010011 6
b1100000000000110010011 >
b1100000000000110010011 @
b11 *
b11 2
b11 ;
b11 H
b10000 =
b10000 A
b1100 <
b1100 ?
b1100 C
b10 L
b0 /
b0 4
b0 G
1.
#400
0.
#450
b1 0
b1 5
b1 E
b1 D
b110011 8
b10101 3
b10101 7
b11000 I
b10101 F
b1 *
b1 2
b1 ;
b1 H
b1010100001000110000110011 1
b1010100001000110000110011 6
b1010100001000110000110011 >
b1010100001000110000110011 @
b11 M
b0 /
b0 4
b0 G
b10100 =
b10100 A
b10000 <
b10000 ?
b10000 C
1.
#500
0.
#550
b1 :
b10110 3
b10110 7
b10000 I
b10110 F
b1 *
b1 2
b1 ;
b1 H
b1011000001001100000110011 1
b1011000001001100000110011 6
b1011000001001100000110011 >
b1011000001001100000110011 @
b11000 =
b11000 A
b10100 <
b10100 ?
b10100 C
b1 b
1.
#600
0.
#650
b10 :
b10111 3
b10111 7
b11000 I
b10111 F
b0 *
b0 2
b0 ;
b0 H
b1011100001010110000110011 1
b1011100001010110000110011 6
b1011100001010110000110011 >
b1011100001010110000110011 @
b1 Z
b11100 =
b11100 A
b11000 <
b11000 ?
b11000 C
1.
#700
0.
#750
b11 :
b11000 3
b11000 7
b10000 I
b11000 F
b1100000001011100000110011 1
b1100000001011100000110011 6
b1100000001011100000110011 >
b1100000001011100000110011 @
b100000 =
b100000 A
b11100 <
b11100 ?
b11100 C
b0 b
1.
#800
0.
#850
b1 *
b1 2
b1 ;
b1 H
b100 :
b11001 3
b11001 7
b11000 I
b11001 F
b1100100001100110000110011 1
b1100100001100110000110011 6
b1100100001100110000110011 >
b1100100001100110000110011 @
b0 Z
b100100 =
b100100 A
b100000 <
b100000 ?
b100000 C
1.
#900
0.
#950
b101 :
b11010 3
b11010 7
b10000 I
b11010 F
b1 *
b1 2
b1 ;
b1 H
b1101000001101100000110011 1
b1101000001101100000110011 6
b1101000001101100000110011 >
b1101000001101100000110011 @
b101000 =
b101000 A
b100100 <
b100100 ?
b100100 C
b1 b
1.
#1000
0.
#1050
b110 :
b11011 3
b11011 7
b11000 I
b11011 F
b1 *
b1 2
b1 ;
b1 H
b1101100001110110000110011 1
b1101100001110110000110011 6
b1101100001110110000110011 >
b1101100001110110000110011 @
b1 Z
b101100 =
b101100 A
b101000 <
b101000 ?
b101000 C
1.
#1100
0.
#1150
b111 :
b11100 3
b11100 7
b10000 I
b11100 F
b0 *
b0 2
b0 ;
b0 H
b1110000001111100000110011 1
b1110000001111100000110011 6
b1110000001111100000110011 >
b1110000001111100000110011 @
b110000 =
b110000 A
b101100 <
b101100 ?
b101100 C
b1 b
1.
#1200
0.
#1250
b0 :
b11101 3
b11101 7
b11000 I
b11101 F
b0 0
b0 5
b0 E
b0 D
b1110100000000110000110011 1
b1110100000000110000110011 6
b1110100000000110000110011 >
b1110100000000110000110011 @
b0 Z
b110100 =
b110100 A
b110000 <
b110000 ?
b110000 C
1.
#1300
0.
#1350
b11110 3
b11110 7
b10000 I
b11110 F
b1111000000000100000110011 1
b1111000000000100000110011 6
b1111000000000100000110011 >
b1111000000000100000110011 @
b111000 =
b111000 A
b110100 <
b110100 ?
b110100 C
b0 b
1.
#1400
0.
#1450
b11111 3
b11111 7
b11000 I
b11111 F
b1111100000000110000110011 1
b1111100000000110000110011 6
b1111100000000110000110011 >
b1111100000000110000110011 @
b0 Z
b111100 =
b111100 A
b111000 <
b111000 ?
b111000 C
1.
#1500
0.
#1550
b10010 3
b10010 7
b10000 I
b10010 F
b1001000000000100000110011 1
b1001000000000100000110011 6
b1001000000000100000110011 >
b1001000000000100000110011 @
b1000000 =
b1000000 A
b111100 <
b111100 ?
b111100 C
b0 b
1.
#1600
0.
#1650
b10001 3
b10001 7
b10001 F
b1000100000000100000110011 1
b1000100000000100000110011 6
b1000100000000100000110011 >
b1000100000000100000110011 @
b0 Z
b1000100 =
b1000100 A
b1000000 <
b1000000 ?
b1000000 C
1.
#1700
0.
#1750
b10011 3
b10011 7
b10011 F
b1001100000000100000110011 1
b1001100000000100000110011 6
b1001100000000100000110011 >
b1001100000000100000110011 @
b1001000 =
b1001000 A
b1000100 <
b1000100 ?
b1000100 C
b0 Z
1.
#1800
0.
#1850
b10100 3
b10100 7
b10100 F
b1010000000000100000110011 1
b1010000000000100000110011 6
b1010000000000100000110011 >
b1010000000000100000110011 @
b0 Z
b1001100 =
b1001100 A
b1001000 <
b1001000 ?
b1001000 C
1.
#1900
0.
#1950
b11000 I
b1010000000000110000110011 1
b1010000000000110000110011 6
b1010000000000110000110011 >
b1010000000000110000110011 @
b1010000 =
b1010000 A
b1001100 <
b1001100 ?
b1001100 C
b0 Z
1.
#2000
0.
#2050
b10000 I
b1010000000000100000110011 1
b1010000000000100000110011 6
b1010000000000100000110011 >
b1010000000000100000110011 @
b0 b
b1010100 =
b1010100 A
b1010000 <
b1010000 ?
b1010000 C
1.
#2100
0.
#2150
b11000 I
b1010000000000110000110011 1
b1010000000000110000110011 6
b1010000000000110000110011 >
b1010000000000110000110011 @
b1011000 =
b1011000 A
b1010100 <
b1010100 ?
b1010100 C
b0 Z
1.
#2200
0.
#2250
b10000 I
b1010000000000100000110011 1
b1010000000000100000110011 6
b1010000000000100000110011 >
b1010000000000100000110011 @
b0 b
b1011100 =
b1011100 A
b1011000 <
b1011000 ?
b1011000 C
1.
#2300
0.
#2350
b11000 I
b1010000000000110000110011 1
b1010000000000110000110011 6
b1010000000000110000110011 >
b1010000000000110000110011 @
b1100000 =
b1100000 A
b1011100 <
b1011100 ?
b1011100 C
b0 Z
1.
#2400
0.
#2450
b10000 I
b1010000000000100000110011 1
b1010000000000100000110011 6
b1010000000000100000110011 >
b1010000000000100000110011 @
b0 b
b1100100 =
b1100100 A
b1100000 <
b1100000 ?
b1100000 C
1.
#2500
0.
#2550
b11000 I
b1010000000000110000110011 1
b1010000000000110000110011 6
b1010000000000110000110011 >
b1010000000000110000110011 @
b1101000 =
b1101000 A
b1100100 <
b1100100 ?
b1100100 C
b0 Z
1.
#2600
0.
#2650
b10000 I
b1010000000000100000110011 1
b1010000000000100000110011 6
b1010000000000100000110011 >
b1010000000000100000110011 @
b0 b
b1101100 =
b1101100 A
b1101000 <
b1101000 ?
b1101000 C
1.
#2700
0.
#2750
b1010000000000100000110011 1
b1010000000000100000110011 6
b1010000000000100000110011 >
b1010000000000100000110011 @
b1110000 =
b1110000 A
b1101100 <
b1101100 ?
b1101100 C
b0 Z
1.
#2800
0.
#2850
b1010000000000100000110011 1
b1010000000000100000110011 6
b1010000000000100000110011 >
b1010000000000100000110011 @
b0 Z
b1110100 =
b1110100 A
b1110000 <
b1110000 ?
b1110000 C
1.
#2900
0.
#2950
b1010000000000100000110011 1
b1010000000000100000110011 6
b1010000000000100000110011 >
b1010000000000100000110011 @
b1111000 =
b1111000 A
b1110100 <
b1110100 ?
b1110100 C
b0 Z
1.
#3000
0.
#3050
b1010000000000100000110011 1
b1010000000000100000110011 6
b1010000000000100000110011 >
b1010000000000100000110011 @
b0 Z
b1111100 =
b1111100 A
b1111000 <
b1111000 ?
b1111000 C
1.
#3100
0.
#3150
b1010000000000100000110011 1
b1010000000000100000110011 6
b1010000000000100000110011 >
b1010000000000100000110011 @
b10000000 =
b10000000 A
b1111100 <
b1111100 ?
b1111100 C
b0 Z
1.
#3200
0.
#3250
b1010000000000100000110011 1
b1010000000000100000110011 6
b1010000000000100000110011 >
b1010000000000100000110011 @
b0 Z
b10000100 =
b10000100 A
b10000000 <
b10000000 ?
b10000000 C
1.
#3300
0.
#3350
b1010000000000100000110011 1
b1010000000000100000110011 6
b1010000000000100000110011 >
b1010000000000100000110011 @
b10001000 =
b10001000 A
b10000100 <
b10000100 ?
b10000100 C
b0 Z
1.
#3400
0.
#3450
b1010000000000100000110011 1
b1010000000000100000110011 6
b1010000000000100000110011 >
b1010000000000100000110011 @
b0 Z
b10001100 =
b10001100 A
b10001000 <
b10001000 ?
b10001000 C
1.
#3500
0.
#3550
b1010000000000100000110011 1
b1010000000000100000110011 6
b1010000000000100000110011 >
b1010000000000100000110011 @
b10010000 =
b10010000 A
b10001100 <
b10001100 ?
b10001100 C
b0 Z
1.
#3600
0.
#3650
b1010000000000100000110011 1
b1010000000000100000110011 6
b1010000000000100000110011 >
b1010000000000100000110011 @
b0 Z
b10010100 =
b10010100 A
b10010000 <
b10010000 ?
b10010000 C
1.
#3700
0.
#3750
b1010000000000100000110011 1
b1010000000000100000110011 6
b1010000000000100000110011 >
b1010000000000100000110011 @
b10011000 =
b10011000 A
b10010100 <
b10010100 ?
b10010100 C
b0 Z
1.
