rtl/ld_st_unit.sv
`timescale 1ns/100ps

module ld_st_unit (
  input             clk_i,
  input             rst_n_i,
  input             load_en_i,
  input      [11:0] offset_i,
  input      [ 2:0] funct3_i,
  input      [31:0] rs1_data_i,
  output reg [31:0] ld_address_o
  );

//  assign ld_address_o = rs1_data_i + {{20{offset_i[11]}}, offset_i};
    
  always @(*)
  begin
    ld_address_o = 32'd0;
    if (load_en_i)
    begin
      case (funct3_i)
        3'b010: ld_address_o = rs1_data_i + {{20{offset_i[11]}}, offset_i}; // Add sign-extended offset to content of RS1
//        3'b001: ld_address_o = ;
//        3'b010: ld_address_o = ; 
////        3'b011: ld_address_o = ; 
//        3'b100: ld_address_o = ;
//        3'b101: ld_address_o = ;
//        3'b110: ld_address_o = ;
//        3'b111: ld_address_o = ;  
//        3'b101: ld_address_o = ;
        default: begin end
      endcase
    end
  end


endmodule

rtl/alu.sv
`timescale 1ns/100ps

module alu (
  input              op_type_i,
  input  wire [31:0] rs1_data_i,
  input       [31:0] operand2_i,
  input  wire [ 2:0] funct3_i,
  input  wire [ 4:0] shamt_i,
  output reg  [31:0] alu_result_o
);

//  typedef enum logic [4:0] {ADD, SUB, MUL, DIV, AND, OR, XOR, NOT, LEZ, LTZ, GTZ, EQT, NET} operation_t;
//  parameter logic [6:0] RTYPE = 7'b0110011;
//  parameter logic [6:0] ITYPE = 7'b0010011;

//
//funct7   rs2    rs1  funct3  rd  opcode
//0000000  rs2    rs1  000     rd  0110011  ADD
//0100000  rs2    rs1  000     rd  0110011  SUB
//0000000  rs2    rs1  001     rd  0110011  SLL
//0000000  rs2    rs1  010     rd  0110011  SLT
//0000000  rs2    rs1  011     rd  0110011  SLTU
//0000000  rs2    rs1  100     rd  0110011  XOR
//0000000  rs2    rs1  101     rd  0110011  SRL
//0100000  rs2    rs1  101     rd  0110011  SRA
//0000000  rs2    rs1  110     rd  0110011  OR
//0000000  rs2    rs1  111     rd  0110011  AND

  always @(*) 
  begin
    case (funct3_i)
      3'b000: alu_result_o = (op_type_i) ? (rs1_data_i - operand2_i) : (rs1_data_i + operand2_i); 
      3'b010: alu_result_o = { 31'd0, ($signed(rs1_data_i) < $signed(operand2_i)) }; 
      3'b011: alu_result_o = { 31'd0, (rs1_data_i < operand2_i) }; 
      3'b100: alu_result_o = rs1_data_i ^  operand2_i;
      3'b110: alu_result_o = rs1_data_i |  operand2_i;
      3'b111: alu_result_o = rs1_data_i &  operand2_i;  
      3'b001: alu_result_o = (rs1_data_i << shamt_i);
      3'b101: alu_result_o = (op_type_i) ? (rs1_data_i >>> shamt_i) : (rs1_data_i >> shamt_i);
      default:
        alu_result_o = 32'hDEADC0DE; 
    endcase
  end

//Immediate      rs1  f3   rd  opcode
//imm[11:0]      rs1  000  rd  0010011  ADDI
//imm[11:0]      rs1  010  rd  0010011  SLTI
//imm[11:0]      rs1  011  rd  0010011  SLTIU
//imm[11:0]      rs1  100  rd  0010011  XORI
//imm[11:0]      rs1  110  rd  0010011  ORI
//imm[11:0]      rs1  111  rd  0010011  ANDI
//0000000 shamt  rs1  001  rd  0010011  SLLI
//0000000 shamt  rs1  101  rd  0010011  SRLI
//0100000 shamt  rs1  101  rd  0010011  SRAI
 
//  assign zero_o = !(|alu_result_o);

endmodule

rtl/regfile.sv
`timescale 1ns/100ps

module regfile #(parameter NUM_REGS=32)
(
  input          clk,        // Input clock
  input          rst_n,      // Reset (active-low)
  input          wr_en,      // Enable register write
  input   [ 4:0] rs1_i,      // Source register 1
  input   [ 4:0] rs2_i,      // Source register 2
  input   [ 4:0] rd_i,       // Destination register
  input   [31:0] wdata_i,    // Write data in
  output  wire [31:0] rs1_o, // Read data for RS1
  output  wire [31:0] rs2_o  // Read data for RS2
);
    

  reg [31:0] x [0:NUM_REGS-1];
//  logic [31:0] din  [0:NUM_REGS-1];

  always @(posedge clk or negedge rst_n) begin
    if (!rst_n)
    begin
//      din[rd_i] <= 32'd0;
//      x[rd_i] <= 32'd0;
      x[ 0] <= 32'd0;
      x[ 1] <= 32'd0;
      x[ 2] <= 32'd0;
      x[ 3] <= 32'd0;
      x[ 4] <= 32'd0;
      x[ 5] <= 32'd0;
      x[ 6] <= 32'd0;
      x[ 7] <= 32'd0;
      x[ 8] <= 32'd0;
      x[ 9] <= 32'd0;
      x[10] <= 32'd0;
      x[11] <= 32'd0;
      x[12] <= 32'd0;
      x[13] <= 32'd0;
      x[14] <= 32'd0;
      x[15] <= 32'd0;
      x[16] <= 32'd0;
      x[17] <= 32'd0;
      x[18] <= 32'd0;
      x[19] <= 32'd0;
      x[20] <= 32'd0;
      x[21] <= 32'd0;
      x[22] <= 32'd0;
      x[23] <= 32'd0;
      x[24] <= 32'd0;
      x[25] <= 32'd0;
      x[26] <= 32'd0;
      x[27] <= 32'd0;
      x[28] <= 32'd0;
      x[29] <= 32'd0;
      x[30] <= 32'd0;
      x[31] <= 32'd0;
    end
    else if (wr_en && (rd_i != 5'd0)) begin
//      din[rd_i] <= wdata_i;
      x[rd_i] <= wdata_i;
    end
  end

  assign rs1_o = x[rs1_i];
  assign rs2_o = x[rs2_i];

endmodule

rtl/decode.sv
`timescale 1ns/100ps

module decode 
  (
    input              clk_i,
    input              rst_n_i,
    input              wr_en_i,
    input       [31:0] instruction_i,
    input       [31:0] alu_result_i,
    input       [31:0] load_data_i,
    output      [ 2:0] funct3_o,
    output             op_type_o,
    output      [11:0] imm_o,
    output reg  [ 4:0] shamt_o,
    output reg         load_en_o,
    output      [31:0] rs1_data_o,
    output reg  [31:0] operand2_o
  );

  wire [ 6:0] opcode_s;
  wire [31:0] rs2_data_s;
  reg [31:0] rf_wdata_q;
  // Decode: includes a regfile (minimal decode for now) TODO: improve decode
  // stage
  // Instantiation of a register file with 32x 32-bit registers
//  assign rf_wdata_q = load_en_o ? load_data_i : alu_result_i;

//  always @(posedge clk_i or negedge rst_n_i)
  always @*
  begin
//    if (!rst_n_i)
      rf_wdata_q = 32'd0;
//    else
      rf_wdata_q = load_en_o ? load_data_i : alu_result_i;
  end

  regfile regfile_inst(.clk    (clk_i),
                       .rst_n  (rst_n_i),
                       .wr_en  (wr_en_i),
                       .rs1_i  (instruction_i[19:15]),
                       .rs2_i  (instruction_i[24:20]),
                       .rd_i   (instruction_i[11: 7]),
                       .wdata_i(rf_wdata_q),
                       .rs1_o  (rs1_data_o),
                       .rs2_o  (rs2_data_s)
                       );

  assign op_type_o = instruction_i[30];
  assign imm_o     = instruction_i[31:20];
  assign opcode_s  = instruction_i[ 6: 0];
  assign funct3_o  = instruction_i[14:12];

  always @(*)
  begin
    operand2_o   = 32'd0;
    shamt_o      = 5'd0;
    load_en_o    = 1'b0;
    case(opcode_s)
      7'b0110011:
      begin
        operand2_o   = rs2_data_s;
        shamt_o      = rs2_data_s[4:0];
      end
      7'b0010011: 
      begin
        operand2_o   = {{20{imm_o[11]}}, imm_o};
        shamt_o      = instruction_i[24:20];
      end
      7'b0000011: 
      begin
        load_en_o   = 1'b1;
      end
      default: begin end
    endcase
  end
endmodule

rtl/main_memory.sv
`timescale 1ns/100ps

module  main_memory(
  input              clk_i,
  input  wire [31:0] instruction_address_i,
  input  wire [31:0] data_address_i,
  input              data_read_en_i,
  output reg  [31:0] instruction_o, 
  output reg  [31:0] load_data_o 
);

//  reg [31:0] main_mem [0:4095]; // 16KB instruction memory.
  reg [31:0] main_mem [0:1023]; // 16KB instruction memory.

  initial begin
    $readmemb("main.mem", main_mem);
  end

  // memory read process
//  always @(posedge clk_i)
  always @*
  begin
//    instruction_o = 32'd0;
    load_data_o   = 32'd0;
    instruction_o = main_mem[instruction_address_i[9:2]]; // Omitting bits 1:0 since instructions always aligned
    if (data_read_en_i)
    begin
      load_data_o   = main_mem[data_address_i[9:0]]; // Data can be byte/HW/W-aligned
    end
  end

endmodule

rtl/reg32bit.sv
`timescale 1ns/100ps

module reg32bit (
  input        clk,
  input        rst_n,
  input [31:0] reset_value_i,
  input        wr_en_i,
  input  wire [31:0] reg_i,
  output reg  [31:0] reg_o
);


  always @(posedge clk or negedge rst_n) begin
    if (!rst_n)
      reg_o <= reset_value_i;
    else if (wr_en_i)
      reg_o <= reg_i;
    else
      reg_o <= reg_o;
  end

endmodule

rtl/ifu.sv
`timescale 1ns/100ps

// Instruction Fetch Unit
module ifu (
  input   clk,
  input   rst_n,
  output  [31:0] pc_o
//  output  [31:0] instruction_o
);

  wire [31:0] next_pc;
//  wire [31:0] inst;

  // Program Counter 32-bit register
  reg32bit reg32bit_pc_inst(.clk  (clk),
                            .rst_n(rst_n),
                            //.reset_value_i(32'h80000180),
                            .reset_value_i(32'h00000000), // Location of first instruction
                            .wr_en_i(1'b1), // FIXME:PC write_enable tied high for now
                            .reg_i(next_pc),
                            .reg_o(pc_o));

  assign next_pc = pc_o + 32'd4; // Add 4 bytes for the next instruction address



endmodule

rtl/clk_gen.sv
`timescale 1ns/100ps
module clk_gen (output clk);
  reg clk_s; 
/* verilator lint_off INFINITELOOP */
/* verilator lint_off STMTDLY */
    always begin
        
      clk_s = 0;
      forever #5  clk_s = ~clk_s;
    end

   assign clk = clk_s;
/* verilator lint_on STMTDLY */
/* verilator lint_on INFINITELOOP */

endmodule

rtl/cpu_top.sv
`timescale 1ns/100ps

module cpu_top(
  input         rst_n_i,
  input         wr_en_i,
//  input  [ 4:0] rs1_i,
//  input  [ 4:0] rs2_i,
//  input  [ 4:0] wrd_i,
//  input  [ 6:0] alu_op_i,
//  input  [31:0] wdata_i,
//  input  [31:0] mem_rdata_i,
  output [31:0] alu_result_o,
  output        z_flag_o

);

  wire sysclk, op_type_s, data_read_en_s, load_en_s;
  wire [31:0] rs1_data_s, operand2_s, instruction_s, alu_result_s, ld_address_s;
  wire [ 4:0] shamt_s;
  wire [11:0] imm_s;
  wire [ 2:0] funct3_s;
  wire [31:0] pc_s, data_address_s, load_data_s;

  assign alu_result_o = alu_result_s;

  // Instantiation of a clk_gen block
  clk_gen i_clk_gen(.clk(sysclk));

  // Fetch: includes PC
  ifu i_ifu(
    .clk  (sysclk),
    .rst_n(rst_n_i),
    .pc_o (pc_s)
  );

  assign data_address_s = ld_address_s;
  assign data_read_en_s = load_en_s;
  main_memory i_main_memory(
    .clk_i                (sysclk), // TODO: clk isn't used atm.
    .instruction_address_i(pc_s),
    .data_address_i       (data_address_s),
    .data_read_en_i       (data_read_en_s),
    .instruction_o        (instruction_s),
    .load_data_o          (load_data_s)
  );

  decode i_decode(
    .clk_i         (sysclk),
    .rst_n_i       (rst_n_i),
    .wr_en_i       (wr_en_i),
    .instruction_i (instruction_s),
    .alu_result_i  (alu_result_s),
    .load_data_i   (load_data_s),
    .funct3_o      (funct3_s),
    .op_type_o     (op_type_s),
    .imm_o         (imm_s),
    .shamt_o       (shamt_s),
    .load_en_o     (load_en_s),
    .rs1_data_o    (rs1_data_s),
    .operand2_o    (operand2_s)
  );

  // Execute: includes ALU module
  alu i_alu(
    .op_type_i    (op_type_s   ),
    .rs1_data_i   (rs1_data_s  ),
    .operand2_i   (operand2_s  ),// Could be rs2 or immediate
    .funct3_i     (funct3_s    ),
    .shamt_i      (shamt_s     ),
    .alu_result_o (alu_result_s)
  );

  ld_st_unit i_ld_st_unit(
    .clk_i        (sysclk),
    .rst_n_i      (rst_n_i),
    .load_en_i    (load_en_s),
    .funct3_i     (funct3_s),
    .offset_i     (imm_s),
    .rs1_data_i   (rs1_data_s),
    .ld_address_o (ld_address_s)
  
  );

endmodule

tb/tb_top.sv
`timescale 1ns/100ps

module tb_top;

  reg          rst_n;
  reg          wr_en    = 1'b0;
  reg   [ 4:0] rs1_i    = 5'd0;
  reg   [ 4:0] rs2_i    = 5'd0;
  reg   [ 4:0] wrd_i    = 5'd0;
  reg   [31:0] wdata_i  = 32'd0;
//  reg   [ 6:0] alu_op_i = 4'd0;
  integer i;
      
  // Instantiation of a reg32bit block
  cpu_top cpu_top_inst(.rst_n_i(rst_n),
                       .wr_en_i(wr_en),
                       //.rs1_i(rs1_i),
                       //.rs2_i(rs2_i),
                       //.wrd_i(wrd_i),
                       //.alu_op_i(alu_op_i),
                       //.wdata_i(wdata_i),
//                       .mem_rdata_i(32'd0),
                       .alu_result_o(),
                       .z_flag_o());

  // data signals
  //wire  [31:0] rs1_o;
  //wire  [31:0] rs2_o;

  // Generation of dumpfile for GTKWave
   initial begin
    $dumpfile("cpu_dump.vcd");
    $dumpvars(0, tb_top);//, clk_gen_inst, regfile_inst, reg_32bit_inst);
    for (i=0; i<32;i++)
      $dumpvars(0,cpu_top_inst.i_decode.regfile_inst.x[i]);
  end
 
  // Test procedure
  initial begin
    // reset
    rst_n = 1'b0;
    wdata_i  = 32'd0;
    #10
    rst_n = 1'b1;
    #1
    wr_en = 1'b1;
    
    #100
    #10000
//    wrd_i = 5'd13;
//    rs1_i = 5'd13;
//    wdata_i = 32'h00FF00FF;
//    #10
//    alu_op_i = 4'd4;
//    #10
//    wrd_i = 5'd10;
//    wdata_i = 32'h11FF11FF;
//    rs2_i = 5'd10;
//
//    #50
//    alu_op_i = 4'd9;
//    #20
//    wrd_i = 5'd23;
//    rs1_i = 5'd23;
//    wdata_i = 32'hFFFF0000;
//
//    #50
//    wdata_i = 32'hDEADBEEF;
//
//    #50
//    wrd_i = 5'd0;
//    rs1_i = 5'd0;
//    wdata_i = 32'hFFFF0000;

    #50
    rst_n = 1'b0;
    #100
    rst_n = 1'b1;
    #50

    $display("Vacuous Pass!"); // Yeah, that easy!
    $finish;
  end

endmodule

sim/cpu_dump.vcd
$date
	Thu Oct  8 15:22:13 2026
$end
$version
	Icarus Verilog
$end
$timescale
	100ps
$end
$scope module tb_top $end
$var reg 5 ! rs1_i [4:0] $end
$var reg 5 " rs2_i [4:0] $end
$var reg 1 # rst_n $end
$var reg 32 $ wdata_i [31:0] $end
$var reg 1 % wr_en $end
$var reg 5 & wrd_i [4:0] $end
$var integer 32 ' i [31:0] $end
$scope module cpu_top_inst $end
$var wire 32 ( alu_result_o [31:0] $end
$var wire 32 ) data_address_s [31:0] $end
$var wire 1 * data_read_en_s $end
$var wire 1 # rst_n_i $end
$var wire 1 % wr_en_i $end
$var wire 1 + z_flag_o $end
$var wire 1 , sysclk $end
$var wire 5 - shamt_s [4:0] $end
$var wire 32 . rs1_data_s [31:0] $end
$var wire 32 / pc_s [31:0] $end
$var wire 32 0 operand2_s [31:0] $end
$var wire 1 1 op_type_s $end
$var wire 1 2 load_en_s $end
$var wire 32 3 load_data_s [31:0] $end
$var wire 32 4 ld_address_s [31:0] $end
$var wire 32 5 instruction_s [31:0] $end
$var wire 12 6 imm_s [11:0] $end
$var wire 3 7 funct3_s [2:0] $end
$var wire 32 8 alu_result_s [31:0] $end
$scope module i_alu $end
$var wire 5 9 shamt_i [4:0] $end
$var wire 32 : rs1_data_i [31:0] $end
$var wire 32 ; operand2_i [31:0] $end
$var wire 1 1 op_type_i $end
$var wire 3 < funct3_i [2:0] $end
$var reg 32 = alu_result_o [31:0] $end
$upscope $end
$scope module i_clk_gen $end
$var wire 1 , clk $end
$var reg 1 > clk_s $end
$upscope $end
$scope module i_decode $end
$var wire 32 ? alu_result_i [31:0] $end
$var wire 1 , clk_i $end
$var wire 1 # rst_n_i $end
$var wire 1 % wr_en_i $end
$var wire 32 @ rs2_data_s [31:0] $end
$var wire 32 A rs1_data_o [31:0] $end
$var wire 7 B opcode_s [6:0] $end
$var wire 1 1 op_type_o $end
$var wire 32 C load_data_i [31:0] $end
$var wire 32 D instruction_i [31:0] $end
$var wire 12 E imm_o [11:0] $end
$var wire 3 F funct3_o [2:0] $end
$var reg 1 2 load_en_o $end
$var reg 32 G operand2_o [31:0] $end
$var reg 32 H rf_wdata_q [31:0] $end
$var reg 5 I shamt_o [4:0] $end
$scope module regfile_inst $end
$var wire 1 , clk $end
$var wire 5 J rd_i [4:0] $end
$var wire 5 K rs1_i [4:0] $end
$var wire 32 L rs1_o [31:0] $end
$var wire 5 M rs2_i [4:0] $end
$var wire 32 N rs2_o [31:0] $end
$var wire 1 # rst_n $end
$var wire 32 O wdata_i [31:0] $end
$var wire 1 % wr_en $end
$var parameter 32 P NUM_REGS $end
$upscope $end
$upscope $end
$scope module i_ifu $end
$var wire 1 , clk $end
$var wire 1 # rst_n $end
$var wire 32 Q pc_o [31:0] $end
$var wire 32 R next_pc [31:0] $end
$scope module reg32bit_pc_inst $end
$var wire 1 , clk $end
$var wire 32 S reg_i [31:0] $end
$var wire 32 T reset_value_i [31:0] $end
$var wire 1 # rst_n $end
$var wire 1 U wr_en_i $end
$var reg 32 V reg_o [31:0] $end
$upscope $end
$upscope $end
$scope module i_ld_st_unit $end
$var wire 1 , clk_i $end
$var wire 3 W funct3_i [2:0] $end
$var wire 1 2 load_en_i $end
$var wire 12 X offset_i [11:0] $end
$var wire 32 Y rs1_data_i [31:0] $end
$var wire 1 # rst_n_i $end
$var reg 32 Z ld_address_o [31:0] $end
$upscope $end
$scope module i_main_memory $end
$var wire 1 , clk_i $end
$var wire 32 [ data_address_i [31:0] $end
$var wire 1 * data_read_en_i $end
$var wire 32 \ instruction_address_i [31:0] $end
$var reg 32 ] instruction_o [31:0] $end
$var reg 32 ^ load_data_o [31:0] $end
$upscope $end
$upscope $end
$upscope $end
$scope module tb_top $end
$scope module cpu_top_inst $end
$scope module i_decode $end
$scope module regfile_inst $end
$var reg 32 _ \x[0] [31:0] $end
$upscope $end
$upscope $end
$upscope $end
$upscope $end
$scope module tb_top $end
$scope module cpu_top_inst $end
$scope module i_decode $end
$scope module regfile_inst $end
$var reg 32 ` \x[1] [31:0] $end
$upscope $end
$upscope $end
$upscope $end
$upscope $end
$scope module tb_top $end
$scope module cpu_top_inst $end
$scope module i_decode $end
$scope module regfile_inst $end
$var reg 32 a \x[2] [31:0] $end
$upscope $end
$upscope $end
$upscope $end
$upscope $end
$scope module tb_top $end
$scope module cpu_top_inst $end
$scope module i_decode $end
$scope module regfile_inst $end
$var reg 32 b \x[3] [31:0] $end
$upscope $end
$upscope $end
$upscope $end
$upscope $end
$scope module tb_top $end
$scope module cpu_top_inst $end
$scope module i_decode $end
$scope module regfile_inst $end
$var reg 32 c \x[4] [31:0] $end
$upscope $end
$upscope $end
$upscope $end
$upscope $end
$scope module tb_top $end
$scope module cpu_top_inst $end
$scope module i_decode $end
$scope module regfile_inst $end
$var reg 32 d \x[5] [31:0] $end
$upscope $end
$upscope $end
$upscope $end
$upscope $end
$scope module tb_top $end
$scope module cpu_top_inst $end
$scope module i_decode $end
$scope module regfile_inst $end
$var reg 32 e \x[6] [31:0] $end
$upscope $end
$upscope $end
$upscope $end
$upscope $end
$scope module tb_top $end
$scope module cpu_top_inst $end
$scope module i_decode $end
$scope module regfile_inst $end
$var reg 32 f \x[7] [31:0] $end
$upscope $end
$upscope $end
$upscope $end
$upscope $end
$scope module tb_top $end
$scope module cpu_top_inst $end
$scope module i_decode $end
$scope module regfile_inst $end
$var reg 32 g \x[8] [31:0] $end
$upscope $end
$upscope $end
$upscope $end
$upscope $end
$scope module tb_top $end
$scope module cpu_top_inst $end
$scope module i_decode $end
$scope module regfile_inst $end
$var reg 32 h \x[9] [31:0] $end
$upscope $end
$upscope $end
$upscope $end
$upscope $end
$scope module tb_top $end
$scope module cpu_top_inst $end
$scope module i_decode $end
$scope module regfile_inst $end
$var reg 32 i \x[10] [31:0] $end
$upscope $end
$upscope $end
$upscope $end
$upscope $end
$scope module tb_top $end
$scope module cpu_top_inst $end
$scope module i_decode $end
$scope module regfile_inst $end
$var reg 32 j \x[11] [31:0] $end
$upscope $end
$upscope $end
$upscope $end
$upscope $end
$scope module tb_top $end
$scope module cpu_top_inst $end
$scope module i_decode $end
$scope module regfile_inst $end
$var reg 32 k \x[12] [31:0] $end
$upscope $end
$upscope $end
$upscope $end
$upscope $end
$scope module tb_top $end
$scope module cpu_top_inst $end
$scope module i_decode $end
$scope module regfile_inst $end
$var reg 32 l \x[13] [31:0] $end
$upscope $end
$upscope $end
$upscope $end
$upscope $end
$scope module tb_top $end
$scope module cpu_top_inst $end
$scope module i_decode $end
$scope module regfile_inst $end
$var reg 32 m \x[14] [31:0] $end
$upscope $end
$upscope $end
$upscope $end
$upscope $end
$scope module tb_top $end
$scope module cpu_top_inst $end
$scope module i_decode $end
$scope module regfile_inst $end
$var reg 32 n \x[15] [31:0] $end
$upscope $end
$upscope $end
$upscope $end
$upscope $end
$scope module tb_top $end
$scope module cpu_top_inst $end
$scope module i_decode $end
$scope module regfile_inst $end
$var reg 32 o \x[16] [31:0] $end
$upscope $end
$upscope $end
$upscope $end
$upscope $end
$scope module tb_top $end
$scope module cpu_top_inst $end
$scope module i_decode $end
$scope module regfile_inst $end
$var reg 32 p \x[17] [31:0] $end
$upscope $end
$upscope $end
$upscope $end
$upscope $end
$scope module tb_top $end
$scope module cpu_top_inst $end
$scope module i_decode $end
$scope module regfile_inst $end
$var reg 32 q \x[18] [31:0] $end
$upscope $end
$upscope $end
$upscope $end
$upscope $end
$scope module tb_top $end
$scope module cpu_top_inst $end
$scope module i_decode $end
$scope module regfile_inst $end
$var reg 32 r \x[19] [31:0] $end
$upscope $end
$upscope $end
$upscope $end
$upscope $end
$scope module tb_top $end
$scope module cpu_top_inst $end
$scope module i_decode $end
$scope module regfile_inst $end
$var reg 32 s \x[20] [31:0] $end
$upscope $end
$upscope $end
$upscope $end
$upscope $end
$scope module tb_top $end
$scope module cpu_top_inst $end
$scope module i_decode $end
$scope module regfile_inst $end
$var reg 32 t \x[21] [31:0] $end
$upscope $end
$upscope $end
$upscope $end
$upscope $end
$scope module tb_top $end
$scope module cpu_top_inst $end
$scope module i_decode $end
$scope module regfile_inst $end
$var reg 32 u \x[22] [31:0] $end
$upscope $end
$upscope $end
$upscope $end
$upscope $end
$scope module tb_top $end
$scope module cpu_top_inst $end
$scope module i_decode $end
$scope module regfile_inst $end
$var reg 32 v \x[23] [31:0] $end
$upscope $end
$upscope $end
$upscope $end
$upscope $end
$scope module tb_top $end
$scope module cpu_top_inst $end
$scope module i_decode $end
$scope module regfile_inst $end
$var reg 32 w \x[24] [31:0] $end
$upscope $end
$upscope $end
$upscope $end
$upscope $end
$scope module tb_top $end
$scope module cpu_top_inst $end
$scope module i_decode $end
$scope module regfile_inst $end
$var reg 32 x \x[25] [31:0] $end
$upscope $end
$upscope $end
$upscope $end
$upscope $end
$scope module tb_top $end
$scope module cpu_top_inst $end
$scope module i_decode $end
$scope module regfile_inst $end
$var reg 32 y \x[26] [31:0] $end
$upscope $end
$upscope $end
$upscope $end
$upscope $end
$scope module tb_top $end
$scope module cpu_top_inst $end
$scope module i_decode $end
$scope module regfile_inst $end
$var reg 32 z \x[27] [31:0] $end
$upscope $end
$upscope $end
$upscope $end
$upscope $end
$scope module tb_top $end
$scope module cpu_top_inst $end
$scope module i_decode $end
$scope module regfile_inst $end
$var reg 32 { \x[28] [31:0] $end
$upscope $end
$upscope $end
$upscope $end
$upscope $end
$scope module tb_top $end
$scope module cpu_top_inst $end
$scope module i_decode $end
$scope module regfile_inst $end
$var reg 32 | \x[29] [31:0] $end
$upscope $end
$upscope $end
$upscope $end
$upscope $end
$scope module tb_top $end
$scope module cpu_top_inst $end
$scope module i_decode $end
$scope module regfile_inst $end
$var reg 32 } \x[30] [31:0] $end
$upscope $end
$upscope $end
$upscope $end
$upscope $end
$scope module tb_top $end
$scope module cpu_top_inst $end
$scope module i_decode $end
$scope module regfile_inst $end
$var reg 32 ~ \x[31] [31:0] $end
$upscope $end
$upscope $end
$upscope $end
$upscope $end
$enddefinitions $end
$comment Show the parameter values. $end
$dumpall
b100000 P
$end
#0
$dumpvars
b0 ~
b0 }
b0 |
b0 {
b0 z
b0 y
b0 x
b0 w
b0 v
b0 u
b0 t
b0 s
b0 r
b0 q
b0 p
b0 o
b0 n
b0 m
b0 l
b0 k
b0 j
b0 i
b0 h
b0 g
b0 f
b0 e
b0 d
b0 c
b0 b
b0 a
b0 `
b0 _
b0 ^
b1010000001000100000110011 ]
b0 \
b0 [
b0 Z
b0 Y
b10100 X
b0 W
b0 V
1U
b0 T
b100 S
b100 R
b0 Q
b0 O
b0 N
b10100 M
b0 L
b1 K
b10000 J
b0 I
b0 H
b0 G
b0 F
b10100 E
b1010000001000100000110011 D
b0 C
b110011 B
b0 A
b0 @
b0 ?
0>
b0 =
b0 <
b0 ;
b0 :
b0 9
b0 8
b0 7
b10100 6
b1010000001000100000110011 5
b0 4
b0 3
02
01
b0 0
b0 /
b0 .
b0 -
0,
z+
0*
b0 )
b0 (
b100000 '
b0 &
0%
b0 $
0#
b0 "
b0 !
$end
#50
b0 ~
b0 }
b0 |
b0 {
b0 z
b0 y
b0 x
b0 w
b0 v
b0 u
b0 t
b0 s
b0 r
b0 q
b0 p
b0 o
b0 n
b0 m
b0 l
b0 k
b0 j
b0 i
b0 h
b0 g
b0 f
b0 e
b0 d
b0 c
b0 b
b0 a
b0 `
b0 _
1,
1>
#100
0,
0>
1#
#110
1%
#150
b1 H
b1 O
b1 (
b1 8
b1 =
b1 ?
b1 -
b1 9
b1 I
b1 0
b1 ;
b1 G
b10011 B
b1 6
b1 E
b1 X
b1 J
b1 M
b0 K
b100000000000010010011 5
b100000000000010010011 D
b100000000000010010011 ]
b1000 R
b1000 S
b100 /
b100 Q
b100 V
b100 \
b0 o
1,
1>
#200
0,
0>
#250
b10 H
b10 O
b10 (
b10 8
b10 =
b10 ?
b10 6
b10 E
b10 X
b10 J
b10 M
b10 -
b10 9
b10 I
b10 0
b10 ;
b10 G
b1000000000000100010011 5
b1000000000000100010011 D
b1000000000000100010011 ]
b1 `
b0 @
b0 N
b1100 R
b1100 S
b1000 /
b1000 Q
b1000 V
b1000 \
1,
1>
#300
0,
0>
#350
b11 H
b11 O
b11 (
b11 8
b11 =
b11 ?
b11 6
b11 E
b11 X
b11 J
b11 M
b1100000000000110010011 5
b1100000000000110010011 D
b1100000000000110010011 ]
b11 -
b11 9
b11 I
b11 0
b11 ;
b11 G
b10000 R
b10000 S
b1100 /
b1100 Q
b1100 V
b1100 \
b10 a
b0 @
b0 N
1,
1>
#400
0,
0>
#450
b100 H
b100 O
b100 (
b100 8
b100 =
b100 ?
b100 6
b100 E
b100 X
b100 J
b100 M
b100 -
b100 9
b100 I
b100 0
b100 ;
b100 G
b10000000000001000010011 5
b10000000000001000010011 D
b10000000000001000010011 ]
b11 b
b0 @
b0 N
b10100 R
b10100 S
b10000 /
b10000 Q
b10000 V
b10000 \
1,
1>
#500
0,
0>
#550
b101 H
b101 O
b101 (
b101 8
b101 =
b101 ?
b101 6
b101 E
b101 X
b101 J
b101 M
b10100000000001010010011 5
b10100000000001010010011 D
b10100000000001010010011 ]
b101 -
b101 9
b101 I
b101 0
b101 ;
b101 G
b11000 R
b11000 S
b10100 /
b10100 Q
b10100 V
b10100 \
b100 c
b0 @
b0 N
1,
1>
#600
0,
0>
#650
b110 H
b110 O
b110 (
b110 8
b110 =
b110 ?
b110 6
b110 E
b110 X
b110 J
b110 M
b110 -
b110 9
b110 I
b110 0
b110 ;
b110 G
b11000000000001100010011 5
b11000000000001100010011 D
b11000000000001100010011 ]
b101 d
b0 @
b0 N
b11100 R
b11100 S
b11000 /
b11000 Q
b11000 V
b11000 \
1,
1>
#700
0,
0>
#750
b111 H
b111 O
b111 (
b111 8
b111 =
b111 ?
b111 6
b111 E
b111 X
b111 J
b111 M
b11100000000001110010011 5
b11100000000001110010011 D
b11100000000001110010011 ]
b111 -
b111 9
b111 I
b111 0
b111 ;
b111 G
b100000 R
b100000 S
b11100 /
b11100 Q
b11100 V
b11100 \
b110 e
b0 @
b0 N
1,
1>
#800
0,
0>
#850
b1000 H
b1000 O
b1000 (
b1000 8
b1000 =
b1000 ?
b1000 6
b1000 E
b1000 X
b1000 J
b1000 M
b1000 -
b1000 9
b1000 I
b1000 0
b1000 ;
b1000 G
b100000000000010000010011 5
b100000000000010000010011 D
b100000000000010000010011 ]
b111 f
b0 @
b0 N
b100100 R
b100100 S
b100000 /
b100000 Q
b100000 V
b100000 \
1,
1>
#900
0,
0>
#950
b1001 H
b1001 O
b1001 (
b1001 8
b1001 =
b1001 ?
b1001 6
b1001 E
b1001 X
b1001 J
b1001 M
b100100000000010010010011 5
b100100000000010010010011 D
b100100000000010010010011 ]
b1001 -
b1001 9
b1001 I
b1001 0
b1001 ;
b1001 G
b101000 R
b101000 S
b100100 /
b100100 Q
b100100 V
b100100 \
b1000 g
b0 @
b0 N
1,
1>
#1000
0,
0>
#1050
b1010 H
b1010 O
b1010 (
b1010 8
b1010 =
b1010 ?
b1010 6
b1010 E
b1010 X
b1010 J
b1010 M
b1010 -
b1010 9
b1010 I
b1010 0
b1010 ;
b1010 G
b101000000000010100010011 5
b101000000000010100010011 D
b101000000000010100010011 ]
b1001 h
b0 @
b0 N
b101100 R
b101100 S
b101000 /
b101000 Q
b101000 V
b101000 \
1,
1>
#1100
0,
0>
#1150
b11111111111111111111111111111111 H
b11111111111111111111111111111111 O
b1 .
b1 :
b1 A
b1 L
b1 Y
b11111111111111111111111111111111 (
b11111111111111111111111111111111 8
b11111111111111111111111111111111 =
b11111111111111111111111111111111 ?
b110011 B
b10000000010 6
b10000000010 E
b10000000010 X
11
b1011 J
b10 M
b1 K
b1000000001000001000010110110011 5
b1000000001000001000010110110011 D
b1000000001000001000010110110011 ]
b10 -
b10 9
b10 I
b10 0
b10 ;
b10 G
b110000 R
b110000 S
b101100 /
b101100 Q
b101100 V
b101100 \
b1010 i
b10 @
b10 N
1,
1>
#1200
0,
0>
