rtl/alu.sv
`timescale 1ns/100ps

module alu (
  input  wire [31:0] data1_i,
  input  wire [31:0] data2_i,
  input  wire [ 3:0] alu_op_i,
  output wire        zero_o,
  output reg [31:0]  result_o
);

//  typedef enum logic [4:0] {ADD, SUB, MUL, DIV, AND, OR, XOR, NOT, LEZ, LTZ, GTZ, EQT, NET} operation_t;
  localparam logic [4:0] ADD = 4'b0000;
  localparam logic [4:0] SUB = 4'b0001;
  localparam logic [4:0] MUL = 4'b0010;
  localparam logic [4:0] DIV = 4'b0011;
  localparam logic [4:0] AND = 4'b0100;
  localparam logic [4:0] OR  = 4'b0101;
  localparam logic [4:0] XOR = 4'b0110;
  localparam logic [4:0] NOT = 4'b0111;
  localparam logic [4:0] LEZ = 4'b1000;
  localparam logic [4:0] LTZ = 4'b1001;
  localparam logic [4:0] GTZ = 4'b1010;
  localparam logic [4:0] EQT = 4'b1011;
  localparam logic [4:0] NET = 4'b1100;

  always @(*) 
  begin
    case(alu_op_i)
      ADD:
        result_o = data1_i + data2_i; 
      SUB: 
        result_o = data1_i - data2_i; 
      MUL:
        result_o = data1_i * data2_i; 
      DIV:
        result_o = data1_i / data2_i; 
      AND:
        result_o = data1_i & data2_i; 
      OR:
        result_o = data1_i | data2_i; 
      XOR:
        result_o = data1_i ^ data2_i; 
      NOT:
        result_o = !data1_i; 
      LEZ:
        result_o = (data1_i <= 32'd0); 
      LTZ: 
        result_o = (data1_i < 32'd0); 
      GTZ:
        result_o = (data1_i > 32'd0); 
      EQT: 
        result_o = data1_i == data2_i; 
      NET:
        result_o = data1_i != data2_i; 
      default: 
        result_o = data1_i;
    endcase
      
  end

  assign zero_o = !(|result_o);

endmodule

rtl/regfile.sv
`timescale 1ns/100ps

module regfile #(parameter NUM_REGS=32)
(
  input          clk,     // Input clock
  input          rst_n,   // Reset (active-low)
  input          wr_en,   // Enable register write
  input   [ 4:0] rs1_i,   // Read source register 1
  input   [ 4:0] rs2_i,   // Read source register 2
  input   [ 4:0] wrs_i,   // Write register
  input   [31:0] wdata_i, // Write data in
  output  wire [31:0] rs1_o,   // Read data for RS1
  output  wire [31:0] rs2_o    // Read data for RS2
);
    

  reg [31:0] qout [0:NUM_REGS-1];
//  logic [31:0] din  [0:NUM_REGS-1];

  always @(posedge clk or negedge rst_n) begin
    if (!rst_n)
    begin
//      din[wrs_i] <= 32'd0;
//      qout[wrs_i] <= 32'd0;
      qout[0] <= 32'd0;
      qout[1] <= 32'd0;
      qout[2] <= 32'd0;
      qout[3] <= 32'd0;
      qout[4] <= 32'd0;
      qout[5] <= 32'd0;
      qout[6] <= 32'd0;
      qout[7] <= 32'd0;
      qout[8] <= 32'd0;
      qout[9] <= 32'd0;
      qout[10] <= 32'd0;
      qout[11] <= 32'd0;
      qout[12] <= 32'd0;
      qout[13] <= 32'd0;
      qout[14] <= 32'd0;
      qout[15] <= 32'd0;
      qout[16] <= 32'd0;
      qout[17] <= 32'd0;
      qout[18] <= 32'd0;
      qout[19] <= 32'd0;
      qout[20] <= 32'd0;
      qout[21] <= 32'd0;
      qout[22] <= 32'd0;
      qout[23] <= 32'd0;
      qout[24] <= 32'd0;
      qout[25] <= 32'd0;
      qout[26] <= 32'd0;
      qout[27] <= 32'd0;
      qout[28] <= 32'd0;
      qout[29] <= 32'd0;
      qout[30] <= 32'd0;
      qout[31] <= 32'd0;
    end
    else if (wr_en && (wrs_i != 5'd0)) begin
//      din[wrs_i] <= wdata_i;
      qout[wrs_i] <= wdata_i;
    end
  end
    

  assign rs1_o = qout[rs1_i];
  assign rs2_o = qout[rs2_i];

endmodule

rtl/reg32bit.sv
`timescale 1ns/100ps

module reg32bit (
  input        clk,
  input        rst_n,
  input        wr_en,
  input  wire [31:0] reg_i,
  output reg  [31:0] reg_o
);

  
  always @(posedge clk or negedge rst_n) begin
    if (!rst_n)
      reg_o <= 32'h00;
    else if (wr_en)
      reg_o <= reg_i;
    else
      reg_o <= reg_o;
  end
    
endmodule

rtl/inst_mem.sv
`timescale 1ns/100ps

module  instruction_memory(
  input  wire [31:0] address,
  output reg  [31:0] instruction 
);

  reg [31:0] imem [0:255]; // 1KB memory.
  
  initial begin
    $readmemh("inst.mem", imem);
  end

  always @(*)
  begin
    instruction = 32'd0;
    instruction = imem[address[9:2]];
  end

endmodule

rtl/ifu.sv
`timescale 1ns/100ps

module ifu (
  input  wire clk,
  input  wire rst_n,
  output wire [31:0] instruction
);

  wire [31:0] next_pc;
  wire [31:0] pc;
  wire [31:0] inst;

  instruction_memory instruction_memory_inst(.address(pc),
                                             .instruction(instruction));

  reg32bit reg32bit_pc_inst(.clk  (clk),
                            .rst_n(rst_n),
                            .wr_en(1'b1),
                            .reg_i(next_pc),
                            .reg_o(pc));

  assign next_pc = pc + 32'd4;

//  regfile regfile_inst(.clk    (clk),
//                       .rst_n  (rst_n),
//                       .wr_en  (1'b1),
//                       .rs1_i  (instruction[25:21]),
//                       .rs2_i  (instruction[20:16]),
//                       .wrs_i  (instruction[15:11]),
//                       .wdata_i(instruction[15: 0]),
//                       .rs1_o  (),
//                       .rs2_o  ());

//  alu alu_inst(.(),
//               .(),
//               .(),
//               .());


endmodule

rtl/clk_gen.sv
`timescale 1ns/100ps
module clk_gen (output reg clk);
    
    always begin
        
      clk = 0;

      forever #5  clk = ~clk;
    end

endmodule

rtl/cpu_top.sv
`timescale 1ns/100ps

module cpu_top(
  input         rst_n,
  input         wr_en,
//  input  [ 4:0] rs1_i,
//  input  [ 4:0] rs2_i,
//  input  [ 4:0] wrs_i,
  input  [ 3:0] alu_op_i,
  input  [31:0] wdata_i,
  input  [31:0] mem_read_data,
  output [31:0] alu_result_o,
  output        z_flag_o

);

  wire sysclk;
  wire [31:0] rs1_data, rs2_data, instruction;

  // Instantiation of a clk_gen block
  clk_gen clk_gen_inst(.clk(sysclk));

  ifu ifu_inst(.clk(sysclk),
               .rst_n(rst_n),
               .instruction(instruction));

  // Instantiation of a reg32bit block
  regfile regfile_inst(.clk    (sysclk),
                       .rst_n  (rst_n),
                       .wr_en  (wr_en),
                       .rs1_i  (instruction[25:21]),
                       .rs2_i  (instruction[20:16]),
                       .wrs_i  (instruction[15:11]),
                       .wdata_i(wdata_i),
                       .rs1_o  (rs1_data),
                       .rs2_o  (rs2_data));

  alu alu_inst (
                .data1_i  (rs1_data),
                .data2_i  (rs2_data),
                .alu_op_i (alu_op_i),
                .zero_o   (z_flag_o),
                .result_o (alu_result_o)
               );

  endmodule

tb/tb_top.sv
`timescale 1ns/100ps

module tb_top;

  reg          rst_n;
  reg          wr_en = 1'b0;
  reg   [ 4:0] rs1_i = 5'd0;
  reg   [ 4:0] rs2_i = 5'd0;
  reg   [ 4:0] wrs_i = 5'd0;
  reg   [31:0] wdata_i = 32'd0;
  reg   [ 3:0] alu_op_i = 4'd0;
  integer i;
      
  // Instantiation of a reg32bit block
  cpu_top cpu_top_inst(.rst_n(rst_n),
                       .wr_en(wr_en),
                       //.rs1_i(rs1_i),
                       //.rs2_i(rs2_i),
                       //.wrs_i(wrs_i),
                       .wdata_i(wdata_i),
                       .alu_op_i(alu_op_i),
                       .mem_read_data(32'd0),
                       .alu_result_o(),
                       .z_flag_o());

  // data signals
  //wire  [31:0] rs1_o;
  //wire  [31:0] rs2_o;

  // Generation of dumpfile for GTKWave
   initial begin
    $dumpfile("regfile_dump.vcd");
    $dumpvars(0, tb_top);//, clk_gen_inst, regfile_inst, reg_32bit_inst);
    for (i=0; i<32;i++)
      $dumpvars(0,cpu_top_inst.regfile_inst.qout[i]);
  end
 
  // Test procedure
  initial begin
    // reset
    rst_n = 1'b0;
    wdata_i  = 32'd0;
    #50
    rst_n = 1'b1;
    
    #100
    wr_en = 1'b1;
    wrs_i = 5'd13;
    rs1_i = 5'd13;
    wdata_i = 32'h00FF00FF;
    #10
    alu_op_i = 4'd4;
    #10
    wrs_i = 5'd10;
    wdata_i = 32'h11FF11FF;
    rs2_i = 5'd10;

    #50
    alu_op_i = 4'd9;
    #20
    wrs_i = 5'd23;
    rs1_i = 5'd23;
    wdata_i = 32'hFFFF0000;

    #50
    wdata_i = 32'hDEADBEEF;

    #50
    wrs_i = 5'd0;
    rs1_i = 5'd0;
    wdata_i = 32'hFFFF0000;

    #50
    rst_n = 1'b0;
    #100
    rst_n = 1'b1;
    #50

    $display("PASSED!"); // Yeah, that easy!
    $finish;
  end

endmodule

sim/regfile_dump.vcd
$date
	Sat Feb  2 15:20:26 2019
$end
$version
	Icarus Verilog
$end
$timescale
	100ps
$end
$scope module tb_top $end
$var reg 4 ! alu_op_i [3:0] $end
$var reg 5 " rs1_i [4:0] $end
$var reg 5 # rs2_i [4:0] $end
$var reg 1 $ rst_n $end
$var reg 32 % wdata_i [31:0] $end
$var reg 1 & wr_en $end
$var reg 5 ' wrs_i [4:0] $end
$var integer 32 ( i [31:0] $end
$scope module cpu_top_inst $end
$var wire 4 ) alu_op_i [3:0] $end
$var wire 32 * mem_read_data [31:0] $end
$var wire 1 $ rst_n $end
$var wire 32 + wdata_i [31:0] $end
$var wire 1 & wr_en $end
$var wire 1 , z_flag_o $end
$var wire 1 - sysclk $end
$var wire 32 . rs2_data [31:0] $end
$var wire 32 / rs1_data [31:0] $end
$var wire 32 0 instruction [31:0] $end
$var wire 32 1 alu_result_o [31:0] $end
$scope module alu_inst $end
$var wire 4 2 alu_op_i [3:0] $end
$var wire 1 , zero_o $end
$var wire 32 3 data2_i [31:0] $end
$var wire 32 4 data1_i [31:0] $end
$var reg 32 5 result_o [31:0] $end
$upscope $end
$scope module clk_gen_inst $end
$var reg 1 - clk $end
$upscope $end
$scope module ifu_inst $end
$var wire 1 - clk $end
$var wire 1 $ rst_n $end
$var wire 32 6 pc [31:0] $end
$var wire 32 7 next_pc [31:0] $end
$var wire 32 8 instruction [31:0] $end
$scope module instruction_memory_inst $end
$var wire 32 9 address [31:0] $end
$var reg 32 : instruction [31:0] $end
$upscope $end
$scope module reg32bit_pc_inst $end
$var wire 1 - clk $end
$var wire 32 ; reg_i [31:0] $end
$var wire 1 $ rst_n $end
$var wire 1 < wr_en $end
$var reg 32 = reg_o [31:0] $end
$upscope $end
$upscope $end
$scope module regfile_inst $end
$var wire 1 - clk $end
$var wire 5 > rs1_i [4:0] $end
$var wire 32 ? rs1_o [31:0] $end
$var wire 5 @ rs2_i [4:0] $end
$var wire 32 A rs2_o [31:0] $end
$var wire 1 $ rst_n $end
$var wire 32 B wdata_i [31:0] $end
$var wire 1 & wr_en $end
$var wire 5 C wrs_i [4:0] $end
$upscope $end
$upscope $end
$upscope $end
$scope module tb_top $end
$scope module cpu_top_inst $end
$scope module regfile_inst $end
$var reg 32 D \qout[0] [31:0] $end
$upscope $end
$upscope $end
$upscope $end
$scope module tb_top $end
$scope module cpu_top_inst $end
$scope module regfile_inst $end
$var reg 32 E \qout[1] [31:0] $end
$upscope $end
$upscope $end
$upscope $end
$scope module tb_top $end
$scope module cpu_top_inst $end
$scope module regfile_inst $end
$var reg 32 F \qout[2] [31:0] $end
$upscope $end
$upscope $end
$upscope $end
$scope module tb_top $end
$scope module cpu_top_inst $end
$scope module regfile_inst $end
$var reg 32 G \qout[3] [31:0] $end
$upscope $end
$upscope $end
$upscope $end
$scope module tb_top $end
$scope module cpu_top_inst $end
$scope module regfile_inst $end
$var reg 32 H \qout[4] [31:0] $end
$upscope $end
$upscope $end
$upscope $end
$scope module tb_top $end
$scope module cpu_top_inst $end
$scope module regfile_inst $end
$var reg 32 I \qout[5] [31:0] $end
$upscope $end
$upscope $end
$upscope $end
$scope module tb_top $end
$scope module cpu_top_inst $end
$scope module regfile_inst $end
$var reg 32 J \qout[6] [31:0] $end
$upscope $end
$upscope $end
$upscope $end
$scope module tb_top $end
$scope module cpu_top_inst $end
$scope module regfile_inst $end
$var reg 32 K \qout[7] [31:0] $end
$upscope $end
$upscope $end
$upscope $end
$scope module tb_top $end
$scope module cpu_top_inst $end
$scope module regfile_inst $end
$var reg 32 L \qout[8] [31:0] $end
$upscope $end
$upscope $end
$upscope $end
$scope module tb_top $end
$scope module cpu_top_inst $end
$scope module regfile_inst $end
$var reg 32 M \qout[9] [31:0] $end
$upscope $end
$upscope $end
$upscope $end
$scope module tb_top $end
$scope module cpu_top_inst $end
$scope module regfile_inst $end
$var reg 32 N \qout[10] [31:0] $end
$upscope $end
$upscope $end
$upscope $end
$scope module tb_top $end
$scope module cpu_top_inst $end
$scope module regfile_inst $end
$var reg 32 O \qout[11] [31:0] $end
$upscope $end
$upscope $end
$upscope $end
$scope module tb_top $end
$scope module cpu_top_inst $end
$scope module regfile_inst $end
$var reg 32 P \qout[12] [31:0] $end
$upscope $end
$upscope $end
$upscope $end
$scope module tb_top $end
$scope module cpu_top_inst $end
$scope module regfile_inst $end
$var reg 32 Q \qout[13] [31:0] $end
$upscope $end
$upscope $end
$upscope $end
$scope module tb_top $end
$scope module cpu_top_inst $end
$scope module regfile_inst $end
$var reg 32 R \qout[14] [31:0] $end
$upscope $end
$upscope $end
$upscope $end
$scope module tb_top $end
$scope module cpu_top_inst $end
$scope module regfile_inst $end
$var reg 32 S \qout[15] [31:0] $end
$upscope $end
$upscope $end
$upscope $end
$scope module tb_top $end
$scope module cpu_top_inst $end
$scope module regfile_inst $end
$var reg 32 T \qout[16] [31:0] $end
$upscope $end
$upscope $end
$upscope $end
$scope module tb_top $end
$scope module cpu_top_inst $end
$scope module regfile_inst $end
$var reg 32 U \qout[17] [31:0] $end
$upscope $end
$upscope $end
$upscope $end
$scope module tb_top $end
$scope module cpu_top_inst $end
$scope module regfile_inst $end
$var reg 32 V \qout[18] [31:0] $end
$upscope $end
$upscope $end
$upscope $end
$scope module tb_top $end
$scope module cpu_top_inst $end
$scope module regfile_inst $end
$var reg 32 W \qout[19] [31:0] $end
$upscope $end
$upscope $end
$upscope $end
$scope module tb_top $end
$scope module cpu_top_inst $end
$scope module regfile_inst $end
$var reg 32 X \qout[20] [31:0] $end
$upscope $end
$upscope $end
$upscope $end
$scope module tb_top $end
$scope module cpu_top_inst $end
$scope module regfile_inst $end
$var reg 32 Y \qout[21] [31:0] $end
$upscope $end
$upscope $end
$upscope $end
$scope module tb_top $end
$scope module cpu_top_inst $end
$scope module regfile_inst $end
$var reg 32 Z \qout[22] [31:0] $end
$upscope $end
$upscope $end
$upscope $end
$scope module tb_top $end
$scope module cpu_top_inst $end
$scope module regfile_inst $end
$var reg 32 [ \qout[23] [31:0] $end
$upscope $end
$upscope $end
$upscope $end
$scope module tb_top $end
$scope module cpu_top_inst $end
$scope module regfile_inst $end
$var reg 32 \ \qout[24] [31:0] $end
$upscope $end
$upscope $end
$upscope $end
$scope module tb_top $end
$scope module cpu_top_inst $end
$scope module regfile_inst $end
$var reg 32 ] \qout[25] [31:0] $end
$upscope $end
$upscope $end
$upscope $end
$scope module tb_top $end
$scope module cpu_top_inst $end
$scope module regfile_inst $end
$var reg 32 ^ \qout[26] [31:0] $end
$upscope $end
$upscope $end
$upscope $end
$scope module tb_top $end
$scope module cpu_top_inst $end
$scope module regfile_inst $end
$var reg 32 _ \qout[27] [31:0] $end
$upscope $end
$upscope $end
$upscope $end
$scope module tb_top $end
$scope module cpu_top_inst $end
$scope module regfile_inst $end
$var reg 32 ` \qout[28] [31:0] $end
$upscope $end
$upscope $end
$upscope $end
$scope module tb_top $end
$scope module cpu_top_inst $end
$scope module regfile_inst $end
$var reg 32 a \qout[29] [31:0] $end
$upscope $end
$upscope $end
$upscope $end
$scope module tb_top $end
$scope module cpu_top_inst $end
$scope module regfile_inst $end
$var reg 32 b \qout[30] [31:0] $end
$upscope $end
$upscope $end
$upscope $end
$scope module tb_top $end
$scope module cpu_top_inst $end
$scope module regfile_inst $end
$var reg 32 c \qout[31] [31:0] $end
$upscope $end
$upscope $end
$upscope $end
$enddefinitions $end
#0
$dumpvars
b0 c
b0 b
b0 a
b0 `
b0 _
b0 ^
b0 ]
b0 \
b0 [
b0 Z
b0 Y
b0 X
b0 W
b0 V
b0 U
b0 T
b0 S
b0 R
b0 Q
b0 P
b0 O
b0 N
b0 M
b0 L
b0 K
b0 J
b0 I
b0 H
b0 G
b0 F
b0 E
b0 D
b1001 C
b0 B
b0 A
b1011 @
b0 ?
b1010 >
b0 =
1<
b100 ;
b1010010110100100000100000 :
b0 9
b1010010110100100000100000 8
b100 7
b0 6
b0 5
b0 4
b0 3
b0 2
b0 1
b1010010110100100000100000 0
b0 /
b0 .
0-
1,
b0 +
b0 *
b0 )
b100000 (
b0 '
0&
b0 %
0$
b0 #
b0 "
b0 !
$end
#50
b0 c
b0 b
b0 a
b0 `
b0 _
b0 ^
b0 ]
b0 \
b0 [
b0 Z
b0 Y
b0 X
b0 W
b0 V
b0 U
b0 T
b0 S
b0 R
b0 Q
b0 P
b0 O
b0 N
b0 M
b0 L
b0 K
b0 J
b0 I
b0 H
b0 G
b0 F
b0 E
b0 D
1-
#100
0-
#150
b0 c
b0 b
b0 a
b0 `
b0 _
b0 ^
b0 ]
b0 \
b0 [
b0 Z
b0 Y
b0 X
b0 W
b0 V
b0 U
b0 T
b0 S
b0 R
b0 Q
b0 P
b0 O
b0 N
b0 M
b0 L
b0 K
b0 J
b0 I
b0 H
b0 G
b0 F
b0 E
b0 D
1-
#200
0-
#250
b0 c
b0 b
b0 a
b0 `
b0 _
b0 ^
b0 ]
b0 \
b0 [
b0 Z
b0 Y
b0 X
b0 W
b0 V
b0 U
b0 T
b0 S
b0 R
b0 Q
b0 P
b0 O
b0 N
b0 M
b0 L
b0 K
b0 J
b0 I
b0 H
b0 G
b0 F
b0 E
b0 D
1-
#300
0-
#350
b0 c
b0 b
b0 a
b0 `
b0 _
b0 ^
b0 ]
b0 \
b0 [
b0 Z
b0 Y
b0 X
b0 W
b0 V
b0 U
b0 T
b0 S
b0 R
b0 Q
b0 P
b0 O
b0 N
b0 M
b0 L
b0 K
b0 J
b0 I
b0 H
b0 G
b0 F
b0 E
b0 D
1-
#400
0-
#450
b0 c
b0 b
b0 a
b0 `
b0 _
b0 ^
b0 ]
b0 \
b0 [
b0 Z
b0 Y
b0 X
b0 W
b0 V
b0 U
b0 T
b0 S
b0 R
b0 Q
b0 P
b0 O
b0 N
b0 M
b0 L
b0 K
b0 J
b0 I
b0 H
b0 G
b0 F
b0 E
b0 D
1-
#500
0-
1$
#550
b1100 @
b1010011000100100000100000 0
b1010011000100100000100000 8
b1010011000100100000100000 :
b1000 7
b1000 ;
b100 6
b100 9
b100 =
1-
#600
0-
#650
b1101 @
b1010011010100100000100000 0
b1010011010100100000100000 8
b1010011010100100000100000 :
b1100 7
b1100 ;
b1000 6
b1000 9
b1000 =
1-
#700
0-
#750
b1011 @
b1100 >
b1100010110100100000100000 0
b1100010110100100000100000 8
b1100010110100100000100000 :
b10000 7
b10000 ;
b1100 6
b1100 9
b1100 =
1-
#800
0-
#850
b1101 >
b1101010110100100000100000 0
b1101010110100100000100000 8
b1101010110100100000100000 :
b10100 7
b10100 ;
b10000 6
b10000 9
b10000 =
1-
#900
0-
#950
b11011 @
b1111 >
b1111110110100100000100000 0
b1111110110100100000100000 8
b1111110110100100000100000 :
b11000 7
b11000 ;
b10100 6
b10100 9
b10100 =
1-
#1000
0-
#1050
b1011 @
b1010 >
b1010010110100100000100000 0
b1010010110100100000100000 8
b1010010110100100000100000 :
b11100 7
b11100 ;
b11000 6
b11000 9
b11000 =
1-
#1100
0-
#1150
b11011 @
b1001 >
b1001110110100100000100000 0
b1001110110100100000100000 8
b1001110110100100000100000 :
b100000 7
b100000 ;
b11100 6
b11100 9
b11100 =
1-
#1200
0-
#1250
b1011 @
b1010 >
b1010010110100100000100000 0
b1010010110100100000100000 8
b1010010110100100000100000 :
b100100 7
b100100 ;
b100000 6
b100000 9
b100000 =
1-
#1300
0-
#1350
b1010010110100100000100000 0
b1010010110100100000100000 8
b1010010110100100000100000 :
b101000 7
b101000 ;
b100100 6
b100100 9
b100100 =
1-
#1400
0-
#1450
b1010010110100100000100000 0
b1010010110100100000100000 8
b1010010110100100000100000 :
b101100 7
b101100 ;
b101000 6
b101000 9
b101000 =
1-
#1500
0-
b111111110000000011111111 %
b111111110000000011111111 +
b111111110000000011111111 B
b1101 "
b1101 '
1&
#1550
b1010010110100100000100000 0
b1010010110100100000100000 8
b1010010110100100000100000 :
b110000 7
b110000 ;
b101100 6
b101100 9
b101100 =
b111111110000000011111111 M
1-
#1600
0-
b100 !
b100 )
b100 2
#1650
b1010010110100100000100000 0
b1010010110100100000100000 8
b1010010110100100000100000 :
b111111110000000011111111 M
b110100 7
b110100 ;
b110000 6
b110000 9
b110000 =
1-
#1700
0-
b1010 #
b10001111111110001000111111111 %
b10001111111110001000111111111 +
b10001111111110001000111111111 B
b1010 '
#1750
b1010010110100100000100000 0
b1010010110100100000100000 8
b1010010110100100000100000 :
b111000 7
b111000 ;
b110100 6
b110100 9
b110100 =
b10001111111110001000111111111 M
1-
#1800
0-
#1850
b1010010110100100000100000 0
b1010010110100100000100000 8
b1010010110100100000100000 :
b10001111111110001000111111111 M
b111100 7
b111100 ;
b111000 6
b111000 9
b111000 =
1-
#1900
0-
#1950
b1010010110100100000100000 0
b1010010110100100000100000 8
b1010010110100100000100000 :
b1000000 7
b1000000 ;
b111100 6
b111100 9
b111100 =
b10001111111110001000111111111 M
1-
#2000
0-
#2050
b1010010110100100000100000 0
b1010010110100100000100000 8
b1010010110100100000100000 :
b10001111111110001000111111111 M
b1000100 7
b1000100 ;
b1000000 6
b1000000 9
b1000000 =
1-
#2100
0-
#2150
b1010010110100100000100000 0
b1010010110100100000100000 8
b1010010110100100000100000 :
b1001000 7
b1001000 ;
b1000100 6
b1000100 9
b1000100 =
b10001111111110001000111111111 M
1-
#2200
0-
b1001 !
b1001 )
b1001 2
#2250
b1010010110100100000100000 0
b1010010110100100000100000 8
b1010010110100100000100000 :
b10001111111110001000111111111 M
b1001100 7
b1001100 ;
b1001000 6
b1001000 9
b1001000 =
1-
#2300
0-
#2350
b1010010110100100000100000 0
b1010010110100100000100000 8
b1010010110100100000100000 :
b1010000 7
b1010000 ;
b1001100 6
b1001100 9
b1001100 =
b10001111111110001000111111111 M
1-
#2400
0-
b11111111111111110000000000000000 %
b11111111111111110000000000000000 +
b11111111111111110000000000000000 B
b10111 "
b10111 '
#2450
b1010010110100100000100000 0
b1010010110100100000100000 8
b1010010110100100000100000 :
b11111111111111110000000000000000 M
b1010100 7
b1010100 ;
b1010000 6
b1010000 9
b1010000 =
1-
#2500
0-
#2550
b1010010110100100000100000 0
b1010010110100100000100000 8
b1010010110100100000100000 :
b1011000 7
b1011000 ;
b1010100 6
b1010100 9
b1010100 =
b11111111111111110000000000000000 M
1-
#2600
0-
#2650
b1010010110100100000100000 0
b1010010110100100000100000 8
b1010010110100100000100000 :
b11111111111111110000000000000000 M
b1011100 7
b1011100 ;
b1011000 6
b1011000 9
b1011000 =
1-
#2700
0-
#2750
b1010010110100100000100000 0
b1010010110100100000100000 8
b1010010110100100000100000 :
b1100000 7
b1100000 ;
b1011100 6
b1011100 9
b1011100 =
b11111111111111110000000000000000 M
1-
#2800
0-
#2850
b1010010110100100000100000 0
b1010010110100100000100000 8
b1010010110100100000100000 :
b11111111111111110000000000000000 M
b1100100 7
b1100100 ;
b1100000 6
b1100000 9
b1100000 =
1-
#2900
0-
b11011110101011011011111011101111 %
b11011110101011011011111011101111 +
b11011110101011011011111011101111 B
#2950
b1010010110100100000100000 0
b1010010110100100000100000 8
b1010010110100100000100000 :
b1101000 7
b1101000 ;
b1100100 6
b1100100 9
b1100100 =
b11011110101011011011111011101111 M
1-
#3000
0-
#3050
b1010010110100100000100000 0
b1010010110100100000100000 8
b1010010110100100000100000 :
b11011110101011011011111011101111 M
b1101100 7
b1101100 ;
b1101000 6
b1101000 9
b1101000 =
1-
#3100
0-
#3150
b1010010110100100000100000 0
b1010010110100100000100000 8
b1010010110100100000100000 :
b1110000 7
b1110000 ;
b1101100 6
b1101100 9
b1101100 =
b11011110101011011011111011101111 M
1-
#3200
0-
#3250
b1010010110100100000100000 0
b1010010110100100000100000 8
b1010010110100100000100000 :
b11011110101011011011111011101111 M
b1110100 7
b1110100 ;
b1110000 6
b1110000 9
b1110000 =
1-
#3300
0-
#3350
b1010010110100100000100000 0
b1010010110100100000100000 8
b1010010110100100000100000 :
b1111000 7
b1111000 ;
b1110100 6
b1110100 9
b1110100 =
b11011110101011011011111011101111 M
1-
#3400
0-
b11111111111111110000000000000000 %
b11111111111111110000000000000000 +
b11111111111111110000000000000000 B
b0 "
b0 '
#3450
b1010010110100100000100000 0
b1010010110100100000100000 8
b1010010110100100000100000 :
b11111111111111110000000000000000 M
b1111100 7
b1111100 ;
b1111000 6
b1111000 9
b1111000 =
1-
#3500
0-
#3550
b1010010110100100000100000 0
b1010010110100100000100000 8
b1010010110100100000100000 :
b10000000 7
b10000000 ;
b1111100 6
b1111100 9
b1111100 =
b11111111111111110000000000000000 M
1-
#3600
0-
#3650
b1010010110100100000100000 0
b1010010110100100000100000 8
b1010010110100100000100000 :
b11111111111111110000000000000000 M
b10000100 7
b10000100 ;
b10000000 6
b10000000 9
b10000000 =
1-
#3700
0-
#3750
b1010010110100100000100000 0
b1010010110100100000100000 8
b1010010110100100000100000 :
b10001000 7
b10001000 ;
b10000100 6
b10000100 9
b10000100 =
b11111111111111110000000000000000 M
1-
#3800
0-
#3850
b1010010110100100000100000 0
b1010010110100100000100000 8
b1010010110100100000100000 :
b11111111111111110000000000000000 M
b10001100 7
b10001100 ;
b10001000 6
b10001000 9
b10001000 =
1-
#3900
b1010010110100100000100000 0
b1010010110100100000100000 8
b1010010110100100000100000 :
b100 7
b100 ;
b0 6
b0 9
b0 =
b0 c
b0 b
b0 a
b0 `
b0 _
b0 ^
b0 ]
b0 \
b0 [
b0 Z
b0 Y
b0 X
b0 W
b0 V
b0 U
b0 T
b0 S
b0 R
b0 Q
b0 P
b0 O
b0 N
b0 M
b0 L
b0 K
b0 J
b0 I
b0 H
b0 G
b0 F
b0 E
b0 D
0-
0$
#3950
b0 c
b0 b
b0 a
b0 `
b0 _
b0 ^
b0 ]
b0 \
b0 [
b0 Z
b0 Y
b0 X
b0 W
b0 V
b0 U
b0 T
b0 S
b0 R
b0 Q
b0 P
b0 O
b0 N
b0 M
b0 L
b0 K
b0 J
b0 I
b0 H
b0 G
b0 F
b0 E
b0 D
1-
#4000
0-
#4050
b0 c
b0 b
b0 a
b0 `
b0 _
b0 ^
b0 ]
b0 \
b0 [
b0 Z
b0 Y
b0 X
b0 W
b0 V
b0 U
b0 T
b0 S
b0 R
b0 Q
b0 P
b0 O
b0 N
b0 M
b0 L
b0 K
b0 J
b0 I
b0 H
b0 G
b0 F
b0 E
b0 D
1-
#4100
0-
#4150
b0 c
b0 b
b0 a
b0 `
b0 _
b0 ^
b0 ]
b0 \
b0 [
b0 Z
b0 Y
b0 X
b0 W
b0 V
b0 U
b0 T
b0 S
b0 R
b0 Q
b0 P
b0 O
b0 N
b0 M
b0 L
b0 K
b0 J
b0 I
b0 H
b0 G
b0 F
b0 E
b0 D
1-
#4200
0-
#4250
b0 c
b0 b
b0 a
b0 `
b0 _
b0 ^
b0 ]
b0 \
b0 [
b0 Z
b0 Y
b0 X
b0 W
b0 V
b0 U
b0 T
b0 S
b0 R
b0 Q
b0 P
b0 O
b0 N
b0 M
b0 L
b0 K
b0 J
b0 I
b0 H
b0 G
b0 F
b0 E
b0 D
1-
#4300
0-
#4350
b0 c
b0 b
b0 a
b0 `
b0 _
b0 ^
b0 ]
b0 \
b0 [
b0 Z
b0 Y
b0 X
b0 W
b0 V
b0 U
b0 T
b0 S
b0 R
b0 Q
b0 P
b0 O
b0 N
b0 M
b0 L
b0 K
b0 J
b0 I
b0 H
b0 G
b0 F
b0 E
b0 D
1-
#4400
0-
#4450
b0 c
b0 b
b0 a
b0 `
b0 _
b0 ^
b0 ]
b0 \
b0 [
b0 Z
b0 Y
b0 X
b0 W
b0 V
b0 U
b0 T
b0 S
b0 R
b0 Q
b0 P
b0 O
b0 N
b0 M
b0 L
b0 K
b0 J
b0 I
b0 H
b0 G
b0 F
b0 E
b0 D
1-
#4500
0-
#4550
b0 c
b0 b
b0 a
b0 `
b0 _
b0 ^
b0 ]
b0 \
b0 [
b0 Z
b0 Y
b0 X
b0 W
b0 V
b0 U
b0 T
b0 S
b0 R
b0 Q
b0 P
b0 O
b0 N
b0 M
b0 L
b0 K
b0 J
b0 I
b0 H
b0 G
b0 F
b0 E
b0 D
1-
#4600
0-
#4650
b0 c
b0 b
b0 a
b0 `
b0 _
b0 ^
b0 ]
b0 \
b0 [
b0 Z
b0 Y
b0 X
b0 W
b0 V
b0 U
b0 T
b0 S
b0 R
b0 Q
b0 P
b0 O
b0 N
b0 M
b0 L
b0 K
b0 J
b0 I
b0 H
b0 G
b0 F
b0 E
b0 D
1-
#4700
0-
#4750
b0 c
b0 b
b0 a
b0 `
b0 _
b0 ^
b0 ]
b0 \
b0 [
b0 Z
b0 Y
b0 X
b0 W
b0 V
b0 U
b0 T
b0 S
b0 R
b0 Q
b0 P
b0 O
b0 N
b0 M
b0 L
b0 K
b0 J
b0 I
b0 H
b0 G
b0 F
b0 E
b0 D
1-
#4800
0-
#4850
b0 c
b0 b
b0 a
b0 `
b0 _
b0 ^
b0 ]
b0 \
b0 [
b0 Z
b0 Y
b0 X
b0 W
b0 V
b0 U
b0 T
b0 S
b0 R
b0 Q
b0 P
b0 O
b0 N
b0 M
b0 L
b0 K
b0 J
b0 I
b0 H
b0 G
b0 F
b0 E
b0 D
1-
#4900
0-
1$
